{"locationIndexItems":[{"isSelected":false,"id":"0142181B-0502-4DD8-B0CD-278D61F3D029","fileName":"Afghanistan.json","displayName":"Afghanistan","isLoaded":false,"loadedDate":666638807.83339798},{"isSelected":false,"id":"A670D7A3-5F2E-47D0-A47A-EE0231615421","fileName":"Albania.json","displayName":"Albania","isLoaded":false,"loadedDate":666638807.84466505},{"isSelected":false,"id":"2F6007BD-4981-4C6F-8835-88CC51794CF3","fileName":"Algeria.json","displayName":"Algeria","isLoaded":false,"loadedDate":666638807.85501206},{"isSelected":false,"id":"71DACE97-8930-4D24-AF01-D187A3851CCA","fileName":"Andorra.json","displayName":"Andorra","isLoaded":false,"loadedDate":666638807.86493194},{"isSelected":false,"id":"895155DB-6309-460D-8C61-BFAE8767AFE8","fileName":"Angola.json","displayName":"Angola","isLoaded":false,"loadedDate":666638807.87558496},{"isSelected":false,"id":"E3F7A3B6-65E0-457D-A43A-5841FFB52C67","fileName":"Antarctica.json","displayName":"Antarctica","isLoaded":false,"loadedDate":666638807.88459694},{"isSelected":false,"id":"256D8EAC-2E19-47CD-97B5-054239F3CB0C","fileName":"Antigua and Barbuda.json","displayName":"Antigua and Barbuda","isLoaded":false,"loadedDate":666638807.89315701},{"isSelected":false,"id":"218494CC-15E5-4E92-A257-85C5EA896ABB","fileName":"Argentina.json","displayName":"Argentina","isLoaded":false,"loadedDate":666638807.90198803},{"isSelected":false,"id":"384292BF-AA0A-4997-A1FE-C6B356B560D0","fileName":"Armenia.json","displayName":"Armenia","isLoaded":false,"loadedDate":666638807.91105199},{"isSelected":false,"id":"3F8A8319-5B7A-45DA-9019-5F831A49F8E3","fileName":"Australia - Australian Capital Territory.json","displayName":"Australia - Australian Capital Territory","isLoaded":false,"loadedDate":666638807.92022097},{"isSelected":false,"id":"B5B89ED5-507D-4AE3-8225-E665520D07A9","fileName":"Australia - New South Wales.json","displayName":"Australia - New South Wales","isLoaded":false,"loadedDate":666638807.92931604},{"isSelected":false,"id":"6353D6F8-8496-4E9C-AC8A-DD255456CF47","fileName":"Australia - Northern Territory.json","displayName":"Australia - Northern Territory","isLoaded":false,"loadedDate":666638807.93834805},{"isSelected":false,"id":"A9E1B88A-478D-47D8-B67E-C7BB274A5B39","fileName":"Australia - Queensland.json","displayName":"Australia - Queensland","isLoaded":false,"loadedDate":666638807.94859302},{"isSelected":false,"id":"AF173B31-4D69-40CE-8AAB-DAE7FF221176","fileName":"Australia - South Australia.json","displayName":"Australia - South Australia","isLoaded":false,"loadedDate":666638807.96192598},{"isSelected":false,"id":"645D10C5-90BD-4668-8B5F-EF6CF78B61A0","fileName":"Australia - Tasmania.json","displayName":"Australia - Tasmania","isLoaded":false,"loadedDate":666638807.97070503},{"isSelected":false,"id":"5DBADD73-153F-4800-81F5-9FC439792543","fileName":"Australia - Victoria.json","displayName":"Australia - Victoria","isLoaded":false,"loadedDate":666638807.97969699},{"isSelected":false,"id":"34DF42DC-F598-4E11-BAED-B7A7E58A8820","fileName":"Australia - Western Australia.json","displayName":"Australia - Western Australia","isLoaded":false,"loadedDate":666638807.98838198},{"isSelected":false,"id":"7EDD15DD-C049-4AAD-8BD5-3E07B9C45202","fileName":"Austria.json","displayName":"Austria","isLoaded":false,"loadedDate":666638807.99697304},{"isSelected":false,"id":"5CEF8A34-E638-4853-9867-0ABB94423E4C","fileName":"Azerbaijan.json","displayName":"Azerbaijan","isLoaded":false,"loadedDate":666638808.00639606},{"isSelected":false,"id":"D08FD804-0FC2-4E8B-82F3-59C876B8C8DD","fileName":"Bahamas.json","displayName":"Bahamas","isLoaded":false,"loadedDate":666638808.016258},{"isSelected":false,"id":"3985B5FF-D439-415F-B3D7-3EA04E0A704D","fileName":"Bahrain.json","displayName":"Bahrain","isLoaded":false,"loadedDate":666638808.02563298},{"isSelected":false,"id":"F600E9C4-573A-4034-8AC6-9F0E6B8A1618","fileName":"Bangladesh.json","displayName":"Bangladesh","isLoaded":false,"loadedDate":666638808.03532398},{"isSelected":false,"id":"2BA0D2BE-D4B6-41FE-9612-E712900655A6","fileName":"Barbados.json","displayName":"Barbados","isLoaded":false,"loadedDate":666638808.04519796},{"isSelected":false,"id":"FBA9DF1C-7BF8-4A2F-8CEC-0B05B6CDD90F","fileName":"Belarus.json","displayName":"Belarus","isLoaded":false,"loadedDate":666638808.06663299},{"isSelected":false,"id":"005CDDF3-EC5D-41B0-ADBE-F19BB212996E","fileName":"Belgium.json","displayName":"Belgium","isLoaded":false,"loadedDate":666638808.07583296},{"isSelected":false,"id":"12DF8849-C830-4519-8649-096CB534475C","fileName":"Belize.json","displayName":"Belize","isLoaded":false,"loadedDate":666638808.08529997},{"isSelected":false,"id":"176406C5-15F9-4A33-A9D8-3C53AC8091B8","fileName":"Benin.json","displayName":"Benin","isLoaded":false,"loadedDate":666638808.09435296},{"isSelected":false,"id":"BE031E42-DEE9-40B5-B448-BDFAE48D50C5","fileName":"Bhutan.json","displayName":"Bhutan","isLoaded":false,"loadedDate":666638808.10424495},{"isSelected":false,"id":"4AF2375F-8B6E-430A-8570-474B7BE821F6","fileName":"Bolivia.json","displayName":"Bolivia","isLoaded":false,"loadedDate":666638808.11290002},{"isSelected":false,"id":"62BCCBA7-8432-42F4-82CD-A531C4AE923E","fileName":"Bosnia and Herzegovina.json","displayName":"Bosnia and Herzegovina","isLoaded":false,"loadedDate":666638808.12199998},{"isSelected":false,"id":"5378C70C-BCBB-46E6-A3D6-895D1CAD0D2D","fileName":"Botswana.json","displayName":"Botswana","isLoaded":false,"loadedDate":666638808.13140094},{"isSelected":false,"id":"865C0F54-3DD5-4723-81B0-6438226E4EDB","fileName":"Brazil.json","displayName":"Brazil","isLoaded":false,"loadedDate":666638808.14086103},{"isSelected":false,"id":"0C50DF4B-EF35-40AE-A8DE-E63B7DE1DE74","fileName":"Brunei.json","displayName":"Brunei","isLoaded":false,"loadedDate":666638808.14970398},{"isSelected":false,"id":"3A22AADE-793A-4FF7-BE67-D007B268F0A4","fileName":"Bulgaria.json","displayName":"Bulgaria","isLoaded":false,"loadedDate":666638808.15882397},{"isSelected":false,"id":"826D7540-1896-4705-90FC-AD2BB5E25062","fileName":"Burkina Faso.json","displayName":"Burkina Faso","isLoaded":false,"loadedDate":666638808.16753101},{"isSelected":false,"id":"04A7ACBC-EBBC-4DEE-89E7-D9ADDE0082BE","fileName":"Burma.json","displayName":"Burma","isLoaded":false,"loadedDate":666638808.17720699},{"isSelected":false,"id":"6C50C64F-F565-41E6-BCFD-EA9DDC2E2202","fileName":"Burundi.json","displayName":"Burundi","isLoaded":false,"loadedDate":666638808.18591499},{"isSelected":false,"id":"61371144-556C-4CE9-ABB3-C5FA36237BC2","fileName":"Cabo Verde.json","displayName":"Cabo Verde","isLoaded":false,"loadedDate":666638808.19452798},{"isSelected":false,"id":"346D2EE0-A20E-4F72-A67E-61ACBE0F94C1","fileName":"Cambodia.json","displayName":"Cambodia","isLoaded":false,"loadedDate":666638808.20430899},{"isSelected":false,"id":"3F94C33C-5845-487F-BCA4-21514529E222","fileName":"Cameroon.json","displayName":"Cameroon","isLoaded":false,"loadedDate":666638808.21303105},{"isSelected":false,"id":"769F78C8-C469-4B98-AC95-6C8571E03AB8","fileName":"Canada - Alberta.json","displayName":"Canada - Alberta","isLoaded":false,"loadedDate":666638808.22207904},{"isSelected":false,"id":"2DD7393C-75AD-4DE5-BB15-A781F47320F9","fileName":"Canada - British Columbia.json","displayName":"Canada - British Columbia","isLoaded":false,"loadedDate":666638808.23064995},{"isSelected":false,"id":"D89230F9-0CB1-4677-9C12-69BF0E60910E","fileName":"Canada - Diamond Princess.json","displayName":"Canada - Diamond Princess","isLoaded":false,"loadedDate":666638808.239483},{"isSelected":false,"id":"D69D1E51-C92B-4CA4-B1FC-74080D11B338","fileName":"Canada - Grand Princess.json","displayName":"Canada - Grand Princess","isLoaded":false,"loadedDate":666638808.24828601},{"isSelected":false,"id":"5098456B-45F3-4C38-B5AF-34253F22EDCE","fileName":"Canada - Manitoba.json","displayName":"Canada - Manitoba","isLoaded":false,"loadedDate":666638808.25702202},{"isSelected":false,"id":"93A1A126-2C90-4330-89CE-0BFF00E7D26A","fileName":"Canada - New Brunswick.json","displayName":"Canada - New Brunswick","isLoaded":false,"loadedDate":666638808.26572204},{"isSelected":false,"id":"D939E4F3-2100-43CD-AFE1-0A4E5902E6CD","fileName":"Canada - Newfoundland and Labrador.json","displayName":"Canada - Newfoundland and Labrador","isLoaded":false,"loadedDate":666638808.27424204},{"isSelected":false,"id":"FB3E2617-E0A9-4102-B477-930BDC1E7B2E","fileName":"Canada - Northwest Territories.json","displayName":"Canada - Northwest Territories","isLoaded":false,"loadedDate":666638808.28287494},{"isSelected":false,"id":"53DF6CA3-E448-47B6-AB1E-EBA030AAF59C","fileName":"Canada - Nova Scotia.json","displayName":"Canada - Nova Scotia","isLoaded":false,"loadedDate":666638808.29239404},{"isSelected":false,"id":"4DC774AF-BC16-4953-9969-6C6E812D645E","fileName":"Canada - Nunavut.json","displayName":"Canada - Nunavut","isLoaded":false,"loadedDate":666638808.30138695},{"isSelected":false,"id":"88E538E8-26C1-4004-BAF4-E242ADAEF292","fileName":"Canada - Ontario.json","displayName":"Canada - Ontario","isLoaded":false,"loadedDate":666638808.31008804},{"isSelected":false,"id":"8656CE0B-2A4C-408B-A0FC-447755F067BC","fileName":"Canada - Prince Edward Island.json","displayName":"Canada - Prince Edward Island","isLoaded":false,"loadedDate":666638808.31908703},{"isSelected":false,"id":"4427E00E-28FC-48E5-BA04-3F11D802E576","fileName":"Canada - Quebec.json","displayName":"Canada - Quebec","isLoaded":false,"loadedDate":666638808.32854998},{"isSelected":false,"id":"5F5A64F2-1F7B-4D17-87DD-72ACDE702368","fileName":"Canada - Repatriated Travellers.json","displayName":"Canada - Repatriated Travellers","isLoaded":false,"loadedDate":666638808.33677602},{"isSelected":false,"id":"04B73B71-8255-4311-A2FB-73044B6C22C6","fileName":"Canada - Saskatchewan.json","displayName":"Canada - Saskatchewan","isLoaded":false,"loadedDate":666638808.34597504},{"isSelected":false,"id":"08BACF4F-5F03-489D-9BFE-6CA23263E363","fileName":"Canada - Yukon.json","displayName":"Canada - Yukon","isLoaded":false,"loadedDate":666638808.35451996},{"isSelected":false,"id":"5073BBB7-B539-4C7E-956C-D50E397CFF69","fileName":"Central African Republic.json","displayName":"Central African Republic","isLoaded":false,"loadedDate":666638808.36356795},{"isSelected":false,"id":"73DC2F70-0ED3-4F1C-B945-2F13087F4EC8","fileName":"Chad.json","displayName":"Chad","isLoaded":false,"loadedDate":666638808.371858},{"isSelected":false,"id":"F617AAA1-B80C-4A96-B40D-5C5990E780B4","fileName":"Chile.json","displayName":"Chile","isLoaded":false,"loadedDate":666638808.38118005},{"isSelected":false,"id":"B1682676-D18D-4641-A8A5-F8BDD7F05659","fileName":"China - Anhui.json","displayName":"China - Anhui","isLoaded":false,"loadedDate":666638808.39230704},{"isSelected":false,"id":"C38CF219-F56A-4878-ABAB-2051ADC2E2DF","fileName":"China - Beijing.json","displayName":"China - Beijing","isLoaded":false,"loadedDate":666638808.40147698},{"isSelected":false,"id":"34E3C216-9F9D-4807-A011-08204CED9A43","fileName":"China - Chongqing.json","displayName":"China - Chongqing","isLoaded":false,"loadedDate":666638808.41019499},{"isSelected":false,"id":"6DC10252-EED4-4985-86BC-DC598C218B9D","fileName":"China - Fujian.json","displayName":"China - Fujian","isLoaded":false,"loadedDate":666638808.41899204},{"isSelected":false,"id":"971D1772-6809-494E-83B6-07145C127194","fileName":"China - Gansu.json","displayName":"China - Gansu","isLoaded":false,"loadedDate":666638808.42779398},{"isSelected":false,"id":"782D5F28-B2B9-413C-A0C9-1AC2F350476E","fileName":"China - Guangdong.json","displayName":"China - Guangdong","isLoaded":false,"loadedDate":666638808.43736005},{"isSelected":false,"id":"8BA7F666-0530-47AB-9C52-06EF29E06B45","fileName":"China - Guangxi.json","displayName":"China - Guangxi","isLoaded":false,"loadedDate":666638808.44617903},{"isSelected":false,"id":"5D7A78CF-1345-468C-8C74-A768BE0C3592","fileName":"China - Guizhou.json","displayName":"China - Guizhou","isLoaded":false,"loadedDate":666638808.45543396},{"isSelected":false,"id":"39A4A4A8-3F76-48EB-BADD-B3C31BF62634","fileName":"China - Hainan.json","displayName":"China - Hainan","isLoaded":false,"loadedDate":666638808.46535099},{"isSelected":false,"id":"99BD1932-21FA-4F74-9B7D-96C9FEED11E8","fileName":"China - Hebei.json","displayName":"China - Hebei","isLoaded":false,"loadedDate":666638808.47386503},{"isSelected":false,"id":"DB8C27FC-C88E-49AB-A6C9-C9241817E162","fileName":"China - Heilongjiang.json","displayName":"China - Heilongjiang","isLoaded":false,"loadedDate":666638808.48266697},{"isSelected":false,"id":"B623B227-CA20-4A8A-BDAB-B3C38C09C13F","fileName":"China - Henan.json","displayName":"China - Henan","isLoaded":false,"loadedDate":666638808.49183798},{"isSelected":false,"id":"E09B6D52-291C-4A89-BB4D-DF9009AE8917","fileName":"China - Hong Kong.json","displayName":"China - Hong Kong","isLoaded":false,"loadedDate":666638808.501122},{"isSelected":false,"id":"B068F3EA-1A4D-48C5-8CD5-A0353A0EDE3C","fileName":"China - Hubei.json","displayName":"China - Hubei","isLoaded":false,"loadedDate":666638808.51018405},{"isSelected":false,"id":"BA76AA29-E201-49EF-9640-5EF5A90C34AE","fileName":"China - Hunan.json","displayName":"China - Hunan","isLoaded":false,"loadedDate":666638808.51913905},{"isSelected":false,"id":"282879B2-2D1F-4BF9-B645-41585D436765","fileName":"China - Inner Mongolia.json","displayName":"China - Inner Mongolia","isLoaded":false,"loadedDate":666638808.52994394},{"isSelected":false,"id":"D44DF038-4EED-4D25-AD59-578FDCDDA31A","fileName":"China - Jiangsu.json","displayName":"China - Jiangsu","isLoaded":false,"loadedDate":666638808.53928494},{"isSelected":false,"id":"75CBB760-413E-45CE-98B9-97A109FBA46A","fileName":"China - Jiangxi.json","displayName":"China - Jiangxi","isLoaded":false,"loadedDate":666638808.54799199},{"isSelected":false,"id":"ADE19414-C1F1-4F9D-BB11-5FB43B6EFAEC","fileName":"China - Jilin.json","displayName":"China - Jilin","isLoaded":false,"loadedDate":666638808.55711901},{"isSelected":false,"id":"D389F698-B846-4C5B-A07B-5206C7D39A34","fileName":"China - Liaoning.json","displayName":"China - Liaoning","isLoaded":false,"loadedDate":666638808.56596804},{"isSelected":false,"id":"BD161AF4-5442-432B-AAFB-3FC2C075A7DE","fileName":"China - Macau.json","displayName":"China - Macau","isLoaded":false,"loadedDate":666638808.57448494},{"isSelected":false,"id":"951167B1-AE5C-4F9F-BC4E-33A40AB21113","fileName":"China - Ningxia.json","displayName":"China - Ningxia","isLoaded":false,"loadedDate":666638808.58331001},{"isSelected":false,"id":"17B65868-B520-48D3-8C78-AD2B2772BCCF","fileName":"China - Qinghai.json","displayName":"China - Qinghai","isLoaded":false,"loadedDate":666638808.59358203},{"isSelected":false,"id":"D25E0F0C-72CC-4860-9C32-11F68FB791FA","fileName":"China - Shaanxi.json","displayName":"China - Shaanxi","isLoaded":false,"loadedDate":666638808.60254395},{"isSelected":false,"id":"04D7F73C-53A0-4589-8D05-E24ED4209F56","fileName":"China - Shandong.json","displayName":"China - Shandong","isLoaded":false,"loadedDate":666638808.61127198},{"isSelected":false,"id":"8FC270A6-0FA6-4C23-842D-CF1799353C9B","fileName":"China - Shanghai.json","displayName":"China - Shanghai","isLoaded":false,"loadedDate":666638808.62065101},{"isSelected":false,"id":"9386044E-B297-432D-AE36-6C0EA7FE2D45","fileName":"China - Shanxi.json","displayName":"China - Shanxi","isLoaded":false,"loadedDate":666638808.62960196},{"isSelected":false,"id":"682986AD-1D1C-40B5-94D6-473251DF346F","fileName":"China - Sichuan.json","displayName":"China - Sichuan","isLoaded":false,"loadedDate":666638808.63927603},{"isSelected":false,"id":"C83FA36B-87EA-4CE3-86CD-40A43BA36F21","fileName":"China - Tianjin.json","displayName":"China - Tianjin","isLoaded":false,"loadedDate":666638808.64906204},{"isSelected":false,"id":"A121A6B0-6498-4634-A886-35CE78F93D7A","fileName":"China - Tibet.json","displayName":"China - Tibet","isLoaded":false,"loadedDate":666638808.65780699},{"isSelected":false,"id":"E0D22D72-5030-4BEA-89E6-DF9BA7A9772D","fileName":"China - Unknown.json","displayName":"China - Unknown","isLoaded":false,"loadedDate":666638808.66656494},{"isSelected":false,"id":"B279D8E3-FCF4-4E45-BE0C-C130D00E41A7","fileName":"China - Xinjiang.json","displayName":"China - Xinjiang","isLoaded":false,"loadedDate":666638808.67565},{"isSelected":false,"id":"0712F8D3-D684-4938-8C69-B76BA8ED5D18","fileName":"China - Yunnan.json","displayName":"China - Yunnan","isLoaded":false,"loadedDate":666638808.68420196},{"isSelected":false,"id":"7C05A6BB-8627-4960-9113-0DB440406A2D","fileName":"China - Zhejiang.json","displayName":"China - Zhejiang","isLoaded":false,"loadedDate":666638808.69306505},{"isSelected":false,"id":"0D1A230B-5469-4525-83D9-0212B28D5FC1","fileName":"Colombia.json","displayName":"Colombia","isLoaded":false,"loadedDate":666638808.702227},{"isSelected":false,"id":"E074A18B-C6F6-4AE3-A90A-C886944F3DB9","fileName":"Comoros.json","displayName":"Comoros","isLoaded":false,"loadedDate":666638808.71109605},{"isSelected":false,"id":"57124D42-A6CA-4F31-8590-941C1ECBE3A0","fileName":"Congo (Brazzaville).json","displayName":"Congo (Brazzaville)","isLoaded":false,"loadedDate":666638808.72006702},{"isSelected":false,"id":"307F1745-1C0B-4522-A585-F02FA37CA1C6","fileName":"Congo (Kinshasa).json","displayName":"Congo (Kinshasa)","isLoaded":false,"loadedDate":666638808.72829401},{"isSelected":false,"id":"51F21CF2-F152-4FFB-8126-04E7AEBBB5C9","fileName":"Costa Rica.json","displayName":"Costa Rica","isLoaded":false,"loadedDate":666638808.73743999},{"isSelected":false,"id":"6C985501-9E0E-4377-963F-6AF356106611","fileName":"Cote d'Ivoire.json","displayName":"Cote d'Ivoire","isLoaded":false,"loadedDate":666638808.74673498},{"isSelected":false,"id":"B4AB91DF-D2E5-40CE-8F3D-D7BD0C90FDF0","fileName":"Croatia.json","displayName":"Croatia","isLoaded":false,"loadedDate":666638808.75552499},{"isSelected":false,"id":"E531F6CC-3841-4F46-9581-18F07F63C61B","fileName":"Cuba.json","displayName":"Cuba","isLoaded":false,"loadedDate":666638808.76420295},{"isSelected":false,"id":"5E22191F-2839-42C0-A2AA-B763E131C627","fileName":"Cyprus.json","displayName":"Cyprus","isLoaded":false,"loadedDate":666638808.77225697},{"isSelected":false,"id":"F242F7E6-0037-41CE-BA35-A8CED221C8BA","fileName":"Czechia.json","displayName":"Czechia","isLoaded":false,"loadedDate":666638808.78084004},{"isSelected":false,"id":"A812CB07-7A8C-472D-B2A0-A552E61D3D09","fileName":"Denmark.json","displayName":"Denmark","isLoaded":false,"loadedDate":666638808.80758703},{"isSelected":false,"id":"F2931609-0396-4D48-9039-59FB612DADC0","fileName":"Denmark - Faroe Islands.json","displayName":"Denmark - Faroe Islands","isLoaded":false,"loadedDate":666638808.78994203},{"isSelected":false,"id":"494DF21D-7510-48B8-9267-8EAFD92C77C2","fileName":"Denmark - Greenland.json","displayName":"Denmark - Greenland","isLoaded":false,"loadedDate":666638808.79886699},{"isSelected":false,"id":"15C46C9E-20BA-4E71-A5BD-C0D8FB88BC9B","fileName":"Diamond Princess.json","displayName":"Diamond Princess","isLoaded":false,"loadedDate":666638808.81554496},{"isSelected":false,"id":"B633A4D4-FDD8-483A-95D4-84F5A1D2D1BB","fileName":"Djibouti.json","displayName":"Djibouti","isLoaded":false,"loadedDate":666638808.82594395},{"isSelected":false,"id":"FD75A102-C4A3-4F74-8659-2DC315ADD282","fileName":"Dominica.json","displayName":"Dominica","isLoaded":false,"loadedDate":666638808.83539999},{"isSelected":false,"id":"B950E331-A652-47C2-B38E-4997689A8AB8","fileName":"Dominican Republic.json","displayName":"Dominican Republic","isLoaded":false,"loadedDate":666638808.84435904},{"isSelected":false,"id":"8FE9FFE5-FF61-4822-82F1-281B631AAB8C","fileName":"Ecuador.json","displayName":"Ecuador","isLoaded":false,"loadedDate":666638808.85307395},{"isSelected":false,"id":"4BACF010-40F2-4FFA-A0FC-3B1816392A5F","fileName":"Egypt.json","displayName":"Egypt","isLoaded":false,"loadedDate":666638808.86416101},{"isSelected":false,"id":"E20184BE-092C-4EFA-8B5D-E110AB2876B9","fileName":"El Salvador.json","displayName":"El Salvador","isLoaded":false,"loadedDate":666638808.87258506},{"isSelected":false,"id":"0723F34F-37E4-4926-BAFE-FAC6E987F91A","fileName":"Equatorial Guinea.json","displayName":"Equatorial Guinea","isLoaded":false,"loadedDate":666638808.88212705},{"isSelected":false,"id":"EE7FDECB-6BE0-42CE-8E91-5229702173B5","fileName":"Eritrea.json","displayName":"Eritrea","isLoaded":false,"loadedDate":666638808.89132595},{"isSelected":false,"id":"82257E56-D5CA-4081-88CC-C6D8BBAB644A","fileName":"Estonia.json","displayName":"Estonia","isLoaded":false,"loadedDate":666638808.90318096},{"isSelected":false,"id":"CFB90EFD-4A82-4B88-86A2-FB6062B9BA33","fileName":"Eswatini.json","displayName":"Eswatini","isLoaded":false,"loadedDate":666638808.91179299},{"isSelected":false,"id":"C87EB174-4304-4A1A-A8D6-22B02DC6656E","fileName":"Ethiopia.json","displayName":"Ethiopia","isLoaded":false,"loadedDate":666638808.92164505},{"isSelected":false,"id":"6C1949CF-1DEA-4F7F-8133-65BD0A3C7D35","fileName":"Fiji.json","displayName":"Fiji","isLoaded":false,"loadedDate":666638808.93072605},{"isSelected":false,"id":"1FF16BC3-7E7D-47A6-ACF2-3BA28446815C","fileName":"Finland.json","displayName":"Finland","isLoaded":false,"loadedDate":666638808.93960702},{"isSelected":false,"id":"89E7F846-9673-4A18-A149-BF41659155C4","fileName":"France.json","displayName":"France","isLoaded":false,"loadedDate":666638809.05816996},{"isSelected":false,"id":"47D55938-DFA7-49B4-B128-786D970B72B8","fileName":"France - French Guiana.json","displayName":"France - French Guiana","isLoaded":false,"loadedDate":666638808.94793797},{"isSelected":false,"id":"4D6DAC02-9C4B-49A3-91D2-41B2F89D9ADF","fileName":"France - French Polynesia.json","displayName":"France - French Polynesia","isLoaded":false,"loadedDate":666638808.95671999},{"isSelected":false,"id":"223864B5-17A1-4BC2-8908-47C9713F7943","fileName":"France - Guadeloupe.json","displayName":"France - Guadeloupe","isLoaded":false,"loadedDate":666638808.96528196},{"isSelected":false,"id":"0D93B529-EEAD-4A98-B5E5-C116C5F019F0","fileName":"France - Martinique.json","displayName":"France - Martinique","isLoaded":false,"loadedDate":666638808.97446299},{"isSelected":false,"id":"17ED0592-33C4-4993-ADCF-7BA61DC91550","fileName":"France - Mayotte.json","displayName":"France - Mayotte","isLoaded":false,"loadedDate":666638808.983675},{"isSelected":false,"id":"F52AD0F1-47C4-4919-B932-94ACA8B43131","fileName":"France - New Caledonia.json","displayName":"France - New Caledonia","isLoaded":false,"loadedDate":666638808.99248302},{"isSelected":false,"id":"1577409A-B2B5-4554-ACF3-82F253CA06D9","fileName":"France - Reunion.json","displayName":"France - Reunion","isLoaded":false,"loadedDate":666638809.00151396},{"isSelected":false,"id":"7CC7A39B-36B7-43CC-BE51-8F4BEFEBA4FA","fileName":"France - Saint Barthelemy.json","displayName":"France - Saint Barthelemy","isLoaded":false,"loadedDate":666638809.01008606},{"isSelected":false,"id":"E519DDC3-1363-4BC2-ADA8-B9DBFE9953C4","fileName":"France - Saint Pierre and Miquelon.json","displayName":"France - Saint Pierre and Miquelon","isLoaded":false,"loadedDate":666638809.02308798},{"isSelected":false,"id":"97E50F25-A30A-4D6C-81E5-6B6DDAD25F4F","fileName":"France - St Martin.json","displayName":"France - St Martin","isLoaded":false,"loadedDate":666638809.03891504},{"isSelected":false,"id":"F71FF4BF-CE6C-4595-A761-C3A65519BE1D","fileName":"France - Wallis and Futuna.json","displayName":"France - Wallis and Futuna","isLoaded":false,"loadedDate":666638809.04882002},{"isSelected":false,"id":"312070EF-441C-430A-8280-40E33639B1E9","fileName":"Gabon.json","displayName":"Gabon","isLoaded":false,"loadedDate":666638809.06777704},{"isSelected":false,"id":"D4844005-8B81-4D5E-9DBF-9E0C762DB042","fileName":"Gambia.json","displayName":"Gambia","isLoaded":false,"loadedDate":666638809.07646},{"isSelected":false,"id":"750F1E9F-D222-429F-9667-863B4211A3BE","fileName":"Georgia.json","displayName":"Georgia","isLoaded":false,"loadedDate":666638809.08506703},{"isSelected":false,"id":"509786DB-AD0E-49E9-93D8-095A074CAD3C","fileName":"Germany.json","displayName":"Germany","isLoaded":false,"loadedDate":666638809.09423602},{"isSelected":false,"id":"9D66002D-191D-4813-BBBB-C58DAB8EED8F","fileName":"Ghana.json","displayName":"Ghana","isLoaded":false,"loadedDate":666638809.10296798},{"isSelected":false,"id":"D2249A8B-54A0-497D-AE52-7263741C548C","fileName":"Greece.json","displayName":"Greece","isLoaded":false,"loadedDate":666638809.11200297},{"isSelected":false,"id":"A8AD31F1-FBB9-49E8-AF25-A54722F88646","fileName":"Grenada.json","displayName":"Grenada","isLoaded":false,"loadedDate":666638809.12069905},{"isSelected":false,"id":"4F16E03A-C9EE-4D9F-BDCB-E9E33F6ED22A","fileName":"Guatemala.json","displayName":"Guatemala","isLoaded":false,"loadedDate":666638809.13989305},{"isSelected":false,"id":"EF71FCBA-7168-49A7-8488-2406E86EBE93","fileName":"Guinea.json","displayName":"Guinea","isLoaded":false,"loadedDate":666638809.14859998},{"isSelected":false,"id":"490D80DA-A0DE-4A57-9617-977697114536","fileName":"Guinea-Bissau.json","displayName":"Guinea-Bissau","isLoaded":false,"loadedDate":666638809.15965295},{"isSelected":false,"id":"B5D6E3AB-B11C-4961-84B3-D6B4C740749B","fileName":"Guyana.json","displayName":"Guyana","isLoaded":false,"loadedDate":666638809.16833198},{"isSelected":false,"id":"883E69B9-8DF7-47CB-BA33-439AD6D0815F","fileName":"Haiti.json","displayName":"Haiti","isLoaded":false,"loadedDate":666638809.17668903},{"isSelected":false,"id":"7A59E648-7E21-4119-89E9-4CA94923D215","fileName":"Holy See.json","displayName":"Holy See","isLoaded":false,"loadedDate":666638809.18587101},{"isSelected":false,"id":"A96DF258-2D72-42BF-A1FB-E384B3AA458C","fileName":"Honduras.json","displayName":"Honduras","isLoaded":false,"loadedDate":666638809.19478595},{"isSelected":false,"id":"83818B2F-6EEF-4DA1-B802-F7A8A0F98766","fileName":"Hungary.json","displayName":"Hungary","isLoaded":false,"loadedDate":666638809.20512199},{"isSelected":false,"id":"89947CF0-04C3-4ABD-A13B-FDF5E17CA819","fileName":"Iceland.json","displayName":"Iceland","isLoaded":false,"loadedDate":666638809.21437001},{"isSelected":false,"id":"BB2DD58A-2917-4975-99EB-B25205E5400B","fileName":"India.json","displayName":"India","isLoaded":false,"loadedDate":666638809.22328103},{"isSelected":false,"id":"E59B0188-9E72-46AF-8633-D0B6772157EB","fileName":"Indonesia.json","displayName":"Indonesia","isLoaded":false,"loadedDate":666638809.23226404},{"isSelected":false,"id":"FC7C8C7A-FDD2-440B-8799-CCBFD3E63E71","fileName":"Iran.json","displayName":"Iran","isLoaded":false,"loadedDate":666638809.24083102},{"isSelected":false,"id":"23F2E4C5-874E-4AE6-BA9E-3B3A6EE3E503","fileName":"Iraq.json","displayName":"Iraq","isLoaded":false,"loadedDate":666638809.24943399},{"isSelected":false,"id":"98854D42-3A1A-461D-8192-44ACBBE8E740","fileName":"Ireland.json","displayName":"Ireland","isLoaded":false,"loadedDate":666638809.25810301},{"isSelected":false,"id":"AF3A566E-F706-4BC6-950A-8F64812635E8","fileName":"Israel.json","displayName":"Israel","isLoaded":false,"loadedDate":666638809.26675606},{"isSelected":false,"id":"9DE8E2D5-62CD-4454-B51B-63C0CAA0DF99","fileName":"Italy.json","displayName":"Italy","isLoaded":false,"loadedDate":666638809.27548301},{"isSelected":false,"id":"736163F2-9510-46D0-9A40-99AD4AA911C6","fileName":"Italy - Abruzzo.json","displayName":"Italy - Abruzzo","isLoaded":false,"loadedDate":666638807.56120598},{"isSelected":false,"id":"EE75A469-DC15-4939-BAE0-47D2696109B9","fileName":"Italy - Basilicata.json","displayName":"Italy - Basilicata","isLoaded":false,"loadedDate":666638807.61714494},{"isSelected":false,"id":"F23CBA89-9C37-4625-BFE1-5507480A7BE0","fileName":"Italy - Calabria.json","displayName":"Italy - Calabria","isLoaded":false,"loadedDate":666638807.74841499},{"isSelected":false,"id":"1D46A296-D283-4E76-A696-B2EFB9EC823D","fileName":"Italy - Campania.json","displayName":"Italy - Campania","isLoaded":false,"loadedDate":666638807.69453001},{"isSelected":false,"id":"BB75189E-9E02-4BEC-A2A1-4736CABF4294","fileName":"Italy - Emilia-Romagna.json","displayName":"Italy - Emilia-Romagna","isLoaded":false,"loadedDate":666638807.57351696},{"isSelected":false,"id":"C8045762-7F6F-4273-B461-6D48CC5FDF4C","fileName":"Italy - Friuli Venezia Giulia.json","displayName":"Italy - Friuli Venezia Giulia","isLoaded":false,"loadedDate":666638807.64018798},{"isSelected":false,"id":"37A64712-8745-4F18-8E5E-90B34F99F0C0","fileName":"Italy - Lazio.json","displayName":"Italy - Lazio","isLoaded":false,"loadedDate":666638807.76629305},{"isSelected":false,"id":"23618663-D9AF-497B-837A-18CDAED22E2F","fileName":"Italy - Liguria.json","displayName":"Italy - Liguria","isLoaded":false,"loadedDate":666638807.58110595},{"isSelected":false,"id":"5CA16451-ED1D-47FE-9205-ED2D9B462278","fileName":"Italy - Lombardia.json","displayName":"Italy - Lombardia","isLoaded":false,"loadedDate":666638807.82272804},{"isSelected":false,"id":"7CD4E5DA-1E48-4A6C-97FD-F9F98F63CA0B","fileName":"Italy - Marche.json","displayName":"Italy - Marche","isLoaded":false,"loadedDate":666638807.80732405},{"isSelected":false,"id":"B3A80ED2-5789-4B05-AE23-06D3F9D56E1D","fileName":"Italy - Molise.json","displayName":"Italy - Molise","isLoaded":false,"loadedDate":666638807.66362},{"isSelected":false,"id":"F708B9FA-3678-4367-90BF-47B0A5C32D6A","fileName":"Italy - P.A. Bolzano.json","displayName":"Italy - P.A. Bolzano","isLoaded":false,"loadedDate":666638807.71252406},{"isSelected":false,"id":"FEE7505E-C7D7-4D8A-8182-AFB9ED99A0BF","fileName":"Italy - P.A. Trento.json","displayName":"Italy - P.A. Trento","isLoaded":false,"loadedDate":666638807.60353804},{"isSelected":false,"id":"31034E58-7AEA-4B8D-AE12-F08EC76E02EA","fileName":"Italy - Piemonte.json","displayName":"Italy - Piemonte","isLoaded":false,"loadedDate":666638807.67694104},{"isSelected":false,"id":"3A6DC696-0480-44E1-8D5B-E9069CA82FCF","fileName":"Italy - Puglia.json","displayName":"Italy - Puglia","isLoaded":false,"loadedDate":666638807.54320896},{"isSelected":false,"id":"22BEA942-7CEB-4751-B2CB-96E3D7A338DB","fileName":"Italy - Sardegna.json","displayName":"Italy - Sardegna","isLoaded":false,"loadedDate":666638807.65416706},{"isSelected":false,"id":"2537EF3E-CBAC-41DD-BCB9-CB851798D0E9","fileName":"Italy - Sicilia.json","displayName":"Italy - Sicilia","isLoaded":false,"loadedDate":666638807.59188902},{"isSelected":false,"id":"DD26E451-BE55-473C-89E4-48666795CB29","fileName":"Italy - Toscana.json","displayName":"Italy - Toscana","isLoaded":false,"loadedDate":666638807.73025596},{"isSelected":false,"id":"E55314D7-C921-421F-856F-20D36271B7A2","fileName":"Italy - Umbria.json","displayName":"Italy - Umbria","isLoaded":false,"loadedDate":666638807.64725804},{"isSelected":false,"id":"DE0525B6-86EF-44C6-9EB6-7132735BE98A","fileName":"Italy - Valle d'Aosta.json","displayName":"Italy - Valle d'Aosta","isLoaded":false,"loadedDate":666638807.79063797},{"isSelected":false,"id":"E43AE086-075C-4CD1-8467-125A05D99F4F","fileName":"Italy - Veneto.json","displayName":"Italy - Veneto","isLoaded":false,"loadedDate":666638807.63252902},{"isSelected":false,"id":"97506A03-0811-4090-82B6-AB50A7D46192","fileName":"Jamaica.json","displayName":"Jamaica","isLoaded":false,"loadedDate":666638809.28437698},{"isSelected":false,"id":"6F549D11-CF57-4541-AF46-78510909E564","fileName":"Japan.json","displayName":"Japan","isLoaded":false,"loadedDate":666638809.29303801},{"isSelected":false,"id":"4E945EC2-28E1-4764-A99A-3FD95A87698F","fileName":"Jordan.json","displayName":"Jordan","isLoaded":false,"loadedDate":666638809.30181706},{"isSelected":false,"id":"C87022FB-251D-4F6F-A395-BAFD5AA54827","fileName":"Kazakhstan.json","displayName":"Kazakhstan","isLoaded":false,"loadedDate":666638809.31072605},{"isSelected":false,"id":"A1401304-644E-4B2B-B146-9CD8C4996258","fileName":"Kenya.json","displayName":"Kenya","isLoaded":false,"loadedDate":666638809.32066202},{"isSelected":false,"id":"8EF81367-EB79-4C2E-993E-8EB4ACC108FD","fileName":"Kiribati.json","displayName":"Kiribati","isLoaded":false,"loadedDate":666638809.32926095},{"isSelected":false,"id":"1FA33C80-8F50-4CBA-A15F-54450E50DCEA","fileName":"Korea, South.json","displayName":"Korea, South","isLoaded":false,"loadedDate":666638809.33815706},{"isSelected":false,"id":"96A77723-CAC6-4C20-A91C-D92583182918","fileName":"Kosovo.json","displayName":"Kosovo","isLoaded":false,"loadedDate":666638809.34618294},{"isSelected":false,"id":"51599322-DD51-4B54-953A-85DB2028E652","fileName":"Kuwait.json","displayName":"Kuwait","isLoaded":false,"loadedDate":666638809.35543501},{"isSelected":false,"id":"0CFD0182-10C4-4DDF-9A07-0FC1775C3E84","fileName":"Kyrgyzstan.json","displayName":"Kyrgyzstan","isLoaded":false,"loadedDate":666638809.36410701},{"isSelected":false,"id":"87306961-D02B-4AB2-B4B9-533DB10B8418","fileName":"Laos.json","displayName":"Laos","isLoaded":false,"loadedDate":666638809.37296295},{"isSelected":false,"id":"035A463B-A632-4291-ABA9-662BFADAEAFE","fileName":"Latvia.json","displayName":"Latvia","isLoaded":false,"loadedDate":666638809.38154805},{"isSelected":false,"id":"9B39052B-9DBF-49F7-834B-758349804E37","fileName":"Lebanon.json","displayName":"Lebanon","isLoaded":false,"loadedDate":666638809.39098096},{"isSelected":false,"id":"225C3A28-B83D-4634-8765-D8E0D1C6E55B","fileName":"Lesotho.json","displayName":"Lesotho","isLoaded":false,"loadedDate":666638809.40158904},{"isSelected":false,"id":"DA258186-FB3C-47EE-B097-EBB7A080DC9F","fileName":"Liberia.json","displayName":"Liberia","isLoaded":false,"loadedDate":666638809.41010296},{"isSelected":false,"id":"8DF39786-CF28-4DFF-9B11-98FEA7DD377F","fileName":"Libya.json","displayName":"Libya","isLoaded":false,"loadedDate":666638809.41908598},{"isSelected":false,"id":"76CD4BC2-6A7A-4D89-8D8A-93EDB172179A","fileName":"Liechtenstein.json","displayName":"Liechtenstein","isLoaded":false,"loadedDate":666638809.42752898},{"isSelected":false,"id":"9942870F-2771-444C-9EF1-DE6932C0FCA4","fileName":"Lithuania.json","displayName":"Lithuania","isLoaded":false,"loadedDate":666638809.44663894},{"isSelected":false,"id":"009E99FC-9AAE-4A18-A916-05195D135206","fileName":"Luxembourg.json","displayName":"Luxembourg","isLoaded":false,"loadedDate":666638809.458992},{"isSelected":false,"id":"24F36CD2-C106-41D9-AFE8-C83B63020233","fileName":"MS Zaandam.json","displayName":"MS Zaandam","isLoaded":false,"loadedDate":666638809.47105598},{"isSelected":false,"id":"1E39DF83-A155-43BE-8E6B-6DD0B4A5587C","fileName":"Madagascar.json","displayName":"Madagascar","isLoaded":false,"loadedDate":666638809.48137903},{"isSelected":false,"id":"EE7750BB-6C81-4FD0-A055-933FF0889569","fileName":"Malawi.json","displayName":"Malawi","isLoaded":false,"loadedDate":666638809.48918104},{"isSelected":false,"id":"A2F8AC5C-904E-47B2-A3EB-E80126DECA01","fileName":"Malaysia.json","displayName":"Malaysia","isLoaded":false,"loadedDate":666638809.498474},{"isSelected":false,"id":"11B337DE-4C6A-4C24-80AB-99F01CD9FF55","fileName":"Maldives.json","displayName":"Maldives","isLoaded":false,"loadedDate":666638809.50729299},{"isSelected":false,"id":"5616B592-DF8B-434F-A1AD-084A0A285F33","fileName":"Mali.json","displayName":"Mali","isLoaded":false,"loadedDate":666638809.51598895},{"isSelected":false,"id":"CDEDD311-F27C-4A84-AAE5-BEF29363BD32","fileName":"Malta.json","displayName":"Malta","isLoaded":false,"loadedDate":666638809.52426398},{"isSelected":false,"id":"A95D3761-1829-4703-A493-88190B3CDEDF","fileName":"Marshall Islands.json","displayName":"Marshall Islands","isLoaded":false,"loadedDate":666638809.53278399},{"isSelected":false,"id":"B08035EB-5B1C-4D73-8D53-D61C44E063EF","fileName":"Mauritania.json","displayName":"Mauritania","isLoaded":false,"loadedDate":666638809.54184401},{"isSelected":false,"id":"668422BC-B2BA-41C3-A808-4B575602235A","fileName":"Mauritius.json","displayName":"Mauritius","isLoaded":false,"loadedDate":666638809.55089295},{"isSelected":false,"id":"C83B239B-0452-4583-8801-6B0664BA62C1","fileName":"Mexico.json","displayName":"Mexico","isLoaded":false,"loadedDate":666638809.56000996},{"isSelected":false,"id":"82E02CA4-F22D-4BD6-933B-8BBC2C99D3D4","fileName":"Micronesia.json","displayName":"Micronesia","isLoaded":false,"loadedDate":666638809.56870699},{"isSelected":false,"id":"C0732655-03A3-431A-AE13-E342F6175A62","fileName":"Moldova.json","displayName":"Moldova","isLoaded":false,"loadedDate":666638809.57486904},{"isSelected":false,"id":"60A859EB-3893-4529-9719-A68C3B82BDAA","fileName":"Monaco.json","displayName":"Monaco","isLoaded":false,"loadedDate":666638809.58366096},{"isSelected":false,"id":"534D1A91-8B59-4199-918B-007F053C9796","fileName":"Mongolia.json","displayName":"Mongolia","isLoaded":false,"loadedDate":666638809.59261096},{"isSelected":false,"id":"8274BF75-FCC4-4E68-A8EF-4200BB3FA068","fileName":"Montenegro.json","displayName":"Montenegro","isLoaded":false,"loadedDate":666638809.60213101},{"isSelected":false,"id":"A52ED8DF-B60B-4E36-88D6-4FCAE0A0FA6B","fileName":"Morocco.json","displayName":"Morocco","isLoaded":false,"loadedDate":666638809.61126602},{"isSelected":false,"id":"A28AE48A-0D49-4BE6-ADAC-BA6E668525F5","fileName":"Mozambique.json","displayName":"Mozambique","isLoaded":false,"loadedDate":666638809.62244701},{"isSelected":false,"id":"5500B942-168E-44BF-9054-EAFF46A9F84C","fileName":"Namibia.json","displayName":"Namibia","isLoaded":false,"loadedDate":666638809.63108099},{"isSelected":false,"id":"1C109B27-EE70-41C9-9B96-3E9C87CBAA74","fileName":"Nepal.json","displayName":"Nepal","isLoaded":false,"loadedDate":666638809.63972998},{"isSelected":false,"id":"91179F61-EC25-4B86-BCB1-B980BDC6BEBE","fileName":"Netherlands.json","displayName":"Netherlands","isLoaded":false,"loadedDate":666638809.69140995},{"isSelected":false,"id":"62CCEA8D-9D55-4ACA-BB03-81E246F20D0A","fileName":"Netherlands - Aruba.json","displayName":"Netherlands - Aruba","isLoaded":false,"loadedDate":666638809.65568602},{"isSelected":false,"id":"8EE3177F-9951-416E-8565-50842DE3FF6C","fileName":"Netherlands - Bonaire, Sint Eustatius and Saba.json","displayName":"Netherlands - Bonaire, Sint Eustatius and Saba","isLoaded":false,"loadedDate":666638809.66470003},{"isSelected":false,"id":"74933E5A-4733-49C5-BE8B-C211D4D87570","fileName":"Netherlands - Curacao.json","displayName":"Netherlands - Curacao","isLoaded":false,"loadedDate":666638809.67375898},{"isSelected":false,"id":"35E818DD-E110-4244-9B36-A80E36509B94","fileName":"Netherlands - Sint Maarten.json","displayName":"Netherlands - Sint Maarten","isLoaded":false,"loadedDate":666638809.68256497},{"isSelected":false,"id":"6AB80D6E-38F8-4FE8-98B8-E3A6B5279D16","fileName":"New Zealand.json","displayName":"New Zealand","isLoaded":false,"loadedDate":666638809.70904696},{"isSelected":false,"id":"F803DB69-7FA0-48BB-8F04-1167FDD10EAA","fileName":"New Zealand - Cook Islands.json","displayName":"New Zealand - Cook Islands","isLoaded":false,"loadedDate":666638809.70035803},{"isSelected":false,"id":"59AFCF2A-E62A-4205-8270-AE1A2300556E","fileName":"Nicaragua.json","displayName":"Nicaragua","isLoaded":false,"loadedDate":666638809.71811104},{"isSelected":false,"id":"C020E80F-344E-443A-A9A4-C095A7249154","fileName":"Niger.json","displayName":"Niger","isLoaded":false,"loadedDate":666638809.72646999},{"isSelected":false,"id":"1221EE9B-AB4B-4ABB-AD92-FDC5076B0160","fileName":"Nigeria.json","displayName":"Nigeria","isLoaded":false,"loadedDate":666638809.73611605},{"isSelected":false,"id":"BE7E622D-1893-45DB-A8AA-E422405E175E","fileName":"North Macedonia.json","displayName":"North Macedonia","isLoaded":false,"loadedDate":666638809.74486697},{"isSelected":false,"id":"373344A7-0420-4913-B63D-B05D67D679D3","fileName":"Norway.json","displayName":"Norway","isLoaded":false,"loadedDate":666638809.75379002},{"isSelected":false,"id":"5C6F2B77-B887-4506-AC90-F2FF8ECA13D2","fileName":"Oman.json","displayName":"Oman","isLoaded":false,"loadedDate":666638809.76277995},{"isSelected":false,"id":"06AE79F5-BC7D-4421-809E-FCBE3C279A13","fileName":"Pakistan.json","displayName":"Pakistan","isLoaded":false,"loadedDate":666638809.77936995},{"isSelected":false,"id":"1C431AED-C853-4B9A-817A-D0BDDF3F9279","fileName":"Palau.json","displayName":"Palau","isLoaded":false,"loadedDate":666638809.78817499},{"isSelected":false,"id":"E49DC814-5B1B-4DCF-91BD-DA14379906B7","fileName":"Panama.json","displayName":"Panama","isLoaded":false,"loadedDate":666638809.79730904},{"isSelected":false,"id":"EFE3BE69-D062-48B9-BE4E-0F7A5EF527D4","fileName":"Papua New Guinea.json","displayName":"Papua New Guinea","isLoaded":false,"loadedDate":666638809.80613697},{"isSelected":false,"id":"08409D8E-2A92-4EF4-B0D7-B056BF8F7F44","fileName":"Paraguay.json","displayName":"Paraguay","isLoaded":false,"loadedDate":666638809.814978},{"isSelected":false,"id":"E3AA0EB1-F355-4CC2-9F12-38A6ABBD59F5","fileName":"Peru.json","displayName":"Peru","isLoaded":false,"loadedDate":666638809.82374704},{"isSelected":false,"id":"3D83666F-A05E-4CD7-BCF4-393BFE777B4F","fileName":"Philippines.json","displayName":"Philippines","isLoaded":false,"loadedDate":666638809.83243406},{"isSelected":false,"id":"13C847C8-8E10-485C-88D5-3AE4459485F8","fileName":"Poland.json","displayName":"Poland","isLoaded":false,"loadedDate":666638809.84129202},{"isSelected":false,"id":"5A03A659-9790-482C-A938-BE5B546C7057","fileName":"Portugal.json","displayName":"Portugal","isLoaded":false,"loadedDate":666638809.85004699},{"isSelected":false,"id":"87B3E4AA-22DC-45ED-9A1E-4C7607DB6EB8","fileName":"Qatar.json","displayName":"Qatar","isLoaded":false,"loadedDate":666638809.858917},{"isSelected":false,"id":"09FD449C-9056-49B1-83ED-49C1F7B5C866","fileName":"Romania.json","displayName":"Romania","isLoaded":false,"loadedDate":666638809.867589},{"isSelected":false,"id":"35975511-B1BA-4CF1-B366-EE2693F9DC4D","fileName":"Russia.json","displayName":"Russia","isLoaded":false,"loadedDate":666638809.87630999},{"isSelected":false,"id":"5CCCA309-96F2-476D-A442-95C9A919CF8D","fileName":"Rwanda.json","displayName":"Rwanda","isLoaded":false,"loadedDate":666638809.88713706},{"isSelected":false,"id":"1192AFA5-CBB0-43CB-822F-96B374924123","fileName":"Saint Kitts and Nevis.json","displayName":"Saint Kitts and Nevis","isLoaded":false,"loadedDate":666638809.895962},{"isSelected":false,"id":"E7E80281-6B64-4544-B4DC-3A2646627782","fileName":"Saint Lucia.json","displayName":"Saint Lucia","isLoaded":false,"loadedDate":666638809.90529203},{"isSelected":false,"id":"6B490BD9-C1C9-4D6A-8B3F-39AA0A1F9B0E","fileName":"Saint Vincent and the Grenadines.json","displayName":"Saint Vincent and the Grenadines","isLoaded":false,"loadedDate":666638809.91406298},{"isSelected":false,"id":"B0378400-73F9-4EFB-B963-FB849BE2EEC7","fileName":"Samoa.json","displayName":"Samoa","isLoaded":false,"loadedDate":666638809.92260599},{"isSelected":false,"id":"208C609E-8001-4BA4-9A6E-7142B8D1DF5D","fileName":"San Marino.json","displayName":"San Marino","isLoaded":false,"loadedDate":666638809.93095195},{"isSelected":false,"id":"7E9A3E90-1D78-49BD-9D9C-F9A1D77E6F2D","fileName":"Sao Tome and Principe.json","displayName":"Sao Tome and Principe","isLoaded":false,"loadedDate":666638809.94019496},{"isSelected":false,"id":"F227C7D1-F2FA-458F-A374-2C2F00235E92","fileName":"Saudi Arabia.json","displayName":"Saudi Arabia","isLoaded":false,"loadedDate":666638809.95430303},{"isSelected":false,"id":"40E2AEC8-1E65-4548-A51F-09B036E3CBFD","fileName":"Senegal.json","displayName":"Senegal","isLoaded":false,"loadedDate":666638809.96266103},{"isSelected":false,"id":"1E786179-5EE9-41C3-BB16-5570A70C2039","fileName":"Serbia.json","displayName":"Serbia","isLoaded":false,"loadedDate":666638809.97681403},{"isSelected":false,"id":"A85A0781-AD8D-4442-A2BC-301CD1B476BB","fileName":"Seychelles.json","displayName":"Seychelles","isLoaded":false,"loadedDate":666638809.98529899},{"isSelected":false,"id":"145714C2-1F13-4998-9DDC-247D89DE149C","fileName":"Sierra Leone.json","displayName":"Sierra Leone","isLoaded":false,"loadedDate":666638809.99373603},{"isSelected":false,"id":"2912B437-DFEA-42D9-BDB9-E9358C17E818","fileName":"Singapore.json","displayName":"Singapore","isLoaded":false,"loadedDate":666638810.00257301},{"isSelected":false,"id":"94973174-5F2C-4AD6-8DF3-1A3E1219966C","fileName":"Slovakia.json","displayName":"Slovakia","isLoaded":false,"loadedDate":666638810.01135099},{"isSelected":false,"id":"1AA5B838-642C-456F-852D-85A03A5776FE","fileName":"Slovenia.json","displayName":"Slovenia","isLoaded":false,"loadedDate":666638810.02052402},{"isSelected":false,"id":"6D386B37-CC17-4FEB-BC89-B3CE36CA8522","fileName":"Solomon Islands.json","displayName":"Solomon Islands","isLoaded":false,"loadedDate":666638810.02888203},{"isSelected":false,"id":"585DC233-3061-419B-AA30-FE3B530177BA","fileName":"Somalia.json","displayName":"Somalia","isLoaded":false,"loadedDate":666638810.03784597},{"isSelected":false,"id":"150ADBA9-44BB-4CE9-8B30-0EB33FEA7FFF","fileName":"South Africa.json","displayName":"South Africa","isLoaded":false,"loadedDate":666638810.05742002},{"isSelected":false,"id":"C210FB89-A1E6-42FC-B0CE-941768CC5FE6","fileName":"South Sudan.json","displayName":"South Sudan","isLoaded":false,"loadedDate":666638810.06640697},{"isSelected":false,"id":"D42EC91F-8F0A-4E82-9A59-5FB87E8937BB","fileName":"Spain.json","displayName":"Spain","isLoaded":false,"loadedDate":666638810.07508898},{"isSelected":false,"id":"840DC5C3-03FA-487C-9A4B-65DBAF743E97","fileName":"Sri Lanka.json","displayName":"Sri Lanka","isLoaded":false,"loadedDate":666638810.08395505},{"isSelected":false,"id":"9A553195-87A6-4265-AB26-50C8347A2908","fileName":"Sudan.json","displayName":"Sudan","isLoaded":false,"loadedDate":666638810.09811699},{"isSelected":false,"id":"358BD54C-EC2D-43CE-9B5E-C8C38C94C74C","fileName":"Summer Olympics 2020.json","displayName":"Summer Olympics 2020","isLoaded":false,"loadedDate":666638810.10678995},{"isSelected":false,"id":"290E7A59-5091-4AA2-859D-ACD8946DCB69","fileName":"Suriname.json","displayName":"Suriname","isLoaded":false,"loadedDate":666638810.116032},{"isSelected":false,"id":"E0E71B7F-8A4C-4DF1-A0E0-9E75B4EFBAD4","fileName":"Sweden.json","displayName":"Sweden","isLoaded":false,"loadedDate":666638810.12714899},{"isSelected":false,"id":"78934011-A52E-402C-B88A-34E6F6D13909","fileName":"Switzerland.json","displayName":"Switzerland","isLoaded":false,"loadedDate":666638810.13712204},{"isSelected":false,"id":"A177E597-86C4-49C2-9440-A3C924DA8223","fileName":"Syria.json","displayName":"Syria","isLoaded":false,"loadedDate":666638810.14573205},{"isSelected":false,"id":"F9CE20BC-FFA7-4564-BA10-BEFC1FF3C201","fileName":"Taiwan*.json","displayName":"Taiwan*","isLoaded":false,"loadedDate":666638810.15462303},{"isSelected":false,"id":"3A230646-1DBB-4C13-BC08-4F59BB2FA503","fileName":"Tajikistan.json","displayName":"Tajikistan","isLoaded":false,"loadedDate":666638810.16353405},{"isSelected":false,"id":"D00477CB-028A-485A-A051-62E09C97D1D1","fileName":"Tanzania.json","displayName":"Tanzania","isLoaded":false,"loadedDate":666638810.17240298},{"isSelected":false,"id":"5F35576E-12C6-4554-8B4D-AC684D20F275","fileName":"Thailand.json","displayName":"Thailand","isLoaded":false,"loadedDate":666638810.18130803},{"isSelected":false,"id":"32A35C0C-67AB-48D0-903C-91BD2AC4E001","fileName":"Timor-Leste.json","displayName":"Timor-Leste","isLoaded":false,"loadedDate":666638810.19024098},{"isSelected":false,"id":"503FF773-EAF4-4223-A926-FBCD3AA7B87A","fileName":"Togo.json","displayName":"Togo","isLoaded":false,"loadedDate":666638810.19859803},{"isSelected":false,"id":"B79E6E6B-4047-4FE5-BBFE-E70B51E7D20A","fileName":"Tonga.json","displayName":"Tonga","isLoaded":false,"loadedDate":666638810.207394},{"isSelected":false,"id":"C14397FC-B9B6-4719-BC6A-26453ABB384F","fileName":"Trinidad and Tobago.json","displayName":"Trinidad and Tobago","isLoaded":false,"loadedDate":666638810.21643198},{"isSelected":false,"id":"5D2E594F-728A-416C-8B88-0DBA38FF94D1","fileName":"Tunisia.json","displayName":"Tunisia","isLoaded":false,"loadedDate":666638810.22499001},{"isSelected":false,"id":"8F7567CF-ADF1-456E-A7D1-CF35A65CF7B5","fileName":"Turkey.json","displayName":"Turkey","isLoaded":false,"loadedDate":666638810.24107504},{"isSelected":false,"id":"546760BC-F16A-4D9D-8034-B33B6E5ED0F5","fileName":"US.json","displayName":"US","isLoaded":false,"loadedDate":666638810.25853801},{"isSelected":false,"id":"E5F3AA51-4957-4A7E-985C-7AFC0F31AC4C","fileName":"Uganda.json","displayName":"Uganda","isLoaded":false,"loadedDate":666638810.26765299},{"isSelected":false,"id":"E89F644F-31B4-487D-A4D1-1C5FF01C4BB5","fileName":"Ukraine.json","displayName":"Ukraine","isLoaded":false,"loadedDate":666638810.29932201},{"isSelected":false,"id":"21D176C1-F176-439C-AB0F-8F60021B96AA","fileName":"United Arab Emirates.json","displayName":"United Arab Emirates","isLoaded":false,"loadedDate":666638810.30789495},{"isSelected":false,"id":"7EFF2684-4A3B-4DC6-9EBB-B6CD76CC2A21","fileName":"United Kingdom.json","displayName":"United Kingdom","isLoaded":false,"loadedDate":666638810.41825104},{"isSelected":false,"id":"0956DF37-6916-4F9D-B626-0A1F57EB28B6","fileName":"United Kingdom - Anguilla.json","displayName":"United Kingdom - Anguilla","isLoaded":false,"loadedDate":666638810.31667197},{"isSelected":false,"id":"820A17EB-0454-4E3D-898D-2714BB676589","fileName":"United Kingdom - Bermuda.json","displayName":"United Kingdom - Bermuda","isLoaded":false,"loadedDate":666638810.32499504},{"isSelected":false,"id":"6730C903-2676-4216-8C89-2860EDAE967A","fileName":"United Kingdom - British Virgin Islands.json","displayName":"United Kingdom - British Virgin Islands","isLoaded":false,"loadedDate":666638810.33360302},{"isSelected":false,"id":"46F00809-BD22-41B6-8389-D1A7B34C1349","fileName":"United Kingdom - Cayman Islands.json","displayName":"United Kingdom - Cayman Islands","isLoaded":false,"loadedDate":666638810.34261},{"isSelected":false,"id":"8BBAEBDC-CB7E-4AD4-9FA5-580C727D48E1","fileName":"United Kingdom - Channel Islands.json","displayName":"United Kingdom - Channel Islands","isLoaded":false,"loadedDate":666638810.35199201},{"isSelected":false,"id":"87404DA9-26EB-4208-AB5D-CA852FD893AE","fileName":"United Kingdom - Falkland Islands (Malvinas).json","displayName":"United Kingdom - Falkland Islands (Malvinas)","isLoaded":false,"loadedDate":666638810.361624},{"isSelected":false,"id":"255D7E63-85AE-467D-A9C5-F5F1F2B6FADB","fileName":"United Kingdom - Gibraltar.json","displayName":"United Kingdom - Gibraltar","isLoaded":false,"loadedDate":666638810.37288702},{"isSelected":false,"id":"A4E5BEE1-BDD8-412C-BD27-2F0C23BD3E76","fileName":"United Kingdom - Isle of Man.json","displayName":"United Kingdom - Isle of Man","isLoaded":false,"loadedDate":666638810.38099599},{"isSelected":false,"id":"874B448B-F8F9-4D35-A861-3218827DB8B2","fileName":"United Kingdom - Montserrat.json","displayName":"United Kingdom - Montserrat","isLoaded":false,"loadedDate":666638810.39188802},{"isSelected":false,"id":"3E5491F4-B2E0-480E-B740-2AE7A3B8BC43","fileName":"United Kingdom - Saint Helena, Ascension and Tristan da Cunha.json","displayName":"United Kingdom - Saint Helena, Ascension and Tristan da Cunha","isLoaded":false,"loadedDate":666638810.40083802},{"isSelected":false,"id":"52DEBB51-B2B5-4D48-9E9E-52ECCD0A0C76","fileName":"United Kingdom - Turks and Caicos Islands.json","displayName":"United Kingdom - Turks and Caicos Islands","isLoaded":false,"loadedDate":666638810.40927505},{"isSelected":false,"id":"0746DB5C-6C14-45CB-B71A-6DA4C58D1F8F","fileName":"Uruguay.json","displayName":"Uruguay","isLoaded":false,"loadedDate":666638810.42711306},{"isSelected":false,"id":"A6C83DAC-7C47-42DB-9A30-96DB58B227B0","fileName":"Uzbekistan.json","displayName":"Uzbekistan","isLoaded":false,"loadedDate":666638810.435673},{"isSelected":false,"id":"EF34C9E4-A442-4B12-A616-CFC5E703FC30","fileName":"Vanuatu.json","displayName":"Vanuatu","isLoaded":false,"loadedDate":666638810.44497299},{"isSelected":false,"id":"3DC0686D-BE98-4D6E-898F-88D10B300202","fileName":"Venezuela.json","displayName":"Venezuela","isLoaded":false,"loadedDate":666638810.45284998},{"isSelected":false,"id":"AFF36945-49EA-4B54-BF69-1C7A5A52039A","fileName":"Vietnam.json","displayName":"Vietnam","isLoaded":false,"loadedDate":666638810.46221399},{"isSelected":false,"id":"75E00200-E616-43E4-9EFB-BB5844A3A05E","fileName":"West Bank and Gaza.json","displayName":"West Bank and Gaza","isLoaded":false,"loadedDate":666638810.47545803},{"isSelected":false,"id":"FF9DE176-11ED-49E1-A6CA-FCFC433FA032","fileName":"Winter Olympics 2022.json","displayName":"Winter Olympics 2022","isLoaded":false,"loadedDate":666638810.48310304},{"isSelected":false,"id":"E8224259-90BA-46AC-B87C-4597A0EC5598","fileName":"Yemen.json","displayName":"Yemen","isLoaded":false,"loadedDate":666638810.48867202},{"isSelected":false,"id":"33F1839B-DCB2-4B82-98E5-4DEB92E5AE25","fileName":"Zambia.json","displayName":"Zambia","isLoaded":false,"loadedDate":666638810.49765897},{"isSelected":false,"id":"E62771D7-4810-41BB-B299-2F376D667A1C","fileName":"Zimbabwe.json","displayName":"Zimbabwe","isLoaded":false,"loadedDate":666638810.50662994}]}