{"locationIndexItems":[{"isSelected":false,"id":"327CE094-B3C5-469D-9F15-92672DFDC3B3","fileName":"Afghanistan.json","displayName":"Afghanistan","isLoaded":false,"loadedDate":666804620.66369903},{"isSelected":false,"id":"CE4701F3-BD47-4377-8B53-54B919F09BD8","fileName":"Albania.json","displayName":"Albania","isLoaded":false,"loadedDate":666804620.66949999},{"isSelected":false,"id":"8B3F5AF7-3A41-4F95-94BC-C0E9799C974B","fileName":"Algeria.json","displayName":"Algeria","isLoaded":false,"loadedDate":666804620.67494297},{"isSelected":false,"id":"0FF19ECB-81D2-4B13-A1D4-00657553C1C4","fileName":"Andorra.json","displayName":"Andorra","isLoaded":false,"loadedDate":666804620.68013406},{"isSelected":false,"id":"3A92D885-CB75-49F1-8663-8BE8F3B61AC2","fileName":"Angola.json","displayName":"Angola","isLoaded":false,"loadedDate":666804620.685009},{"isSelected":false,"id":"1A5FAEE3-DDDD-4A2C-8320-28DD8F855797","fileName":"Antarctica.json","displayName":"Antarctica","isLoaded":false,"loadedDate":666804620.69239497},{"isSelected":false,"id":"A817ADFF-7D2B-4161-8538-BFB3521097B3","fileName":"Antigua and Barbuda.json","displayName":"Antigua and Barbuda","isLoaded":false,"loadedDate":666804620.698174},{"isSelected":false,"id":"FFB18DBE-905E-484E-B598-0F488B65136F","fileName":"Argentina.json","displayName":"Argentina","isLoaded":false,"loadedDate":666804620.70313704},{"isSelected":false,"id":"35BC3A38-84AB-4094-83EB-C1E882ADB106","fileName":"Armenia.json","displayName":"Armenia","isLoaded":false,"loadedDate":666804620.70870197},{"isSelected":false,"id":"87090E7B-141B-41A9-B196-A33E51FA2E36","fileName":"Australia - Australian Capital Territory.json","displayName":"Australia - Australian Capital Territory","isLoaded":false,"loadedDate":666804620.71582603},{"isSelected":false,"id":"ABA2B852-D04F-483B-8FE7-48BF45D5FA81","fileName":"Australia - New South Wales.json","displayName":"Australia - New South Wales","isLoaded":false,"loadedDate":666804620.72127795},{"isSelected":false,"id":"ADDD84BB-FA8E-41FB-93F1-83138554BCBD","fileName":"Australia - Northern Territory.json","displayName":"Australia - Northern Territory","isLoaded":false,"loadedDate":666804620.72767305},{"isSelected":false,"id":"FB559CA3-6712-4FDE-A959-579692430972","fileName":"Australia - Queensland.json","displayName":"Australia - Queensland","isLoaded":false,"loadedDate":666804620.74025905},{"isSelected":false,"id":"A9AC1630-CB7E-41E5-9D1A-968A53CE420C","fileName":"Australia - South Australia.json","displayName":"Australia - South Australia","isLoaded":false,"loadedDate":666804620.75676203},{"isSelected":false,"id":"C591DDC2-6408-4EE4-B6A1-EC4A5BEA3E78","fileName":"Australia - Tasmania.json","displayName":"Australia - Tasmania","isLoaded":false,"loadedDate":666804620.76730204},{"isSelected":false,"id":"F0DE3F0F-EB4E-4938-B162-C9AE65878BF3","fileName":"Australia - Victoria.json","displayName":"Australia - Victoria","isLoaded":false,"loadedDate":666804620.78134},{"isSelected":false,"id":"491E3AC7-6B9F-47BC-9985-81E7C7AFEE0B","fileName":"Australia - Western Australia.json","displayName":"Australia - Western Australia","isLoaded":false,"loadedDate":666804620.79328799},{"isSelected":false,"id":"21F392EE-799B-4CCA-BA66-B84D966CB1A5","fileName":"Austria.json","displayName":"Austria","isLoaded":false,"loadedDate":666804620.80454099},{"isSelected":false,"id":"64698084-F475-4480-BF52-2A8152FA8B1D","fileName":"Azerbaijan.json","displayName":"Azerbaijan","isLoaded":false,"loadedDate":666804620.81623697},{"isSelected":false,"id":"4DABAA72-FE6B-429D-9DBA-B85AF982677C","fileName":"Bahamas.json","displayName":"Bahamas","isLoaded":false,"loadedDate":666804620.82712901},{"isSelected":false,"id":"CF38559B-EA87-4956-AA44-F6478A2D4CE8","fileName":"Bahrain.json","displayName":"Bahrain","isLoaded":false,"loadedDate":666804620.83910406},{"isSelected":false,"id":"7DFD9053-6AB7-4664-ABFD-C76149F2D8DB","fileName":"Bangladesh.json","displayName":"Bangladesh","isLoaded":false,"loadedDate":666804620.85233498},{"isSelected":false,"id":"FDB53E7A-F055-4BD1-9DB7-E40B1A0665AD","fileName":"Barbados.json","displayName":"Barbados","isLoaded":false,"loadedDate":666804620.86702704},{"isSelected":false,"id":"DA2B0963-8A81-4377-BBD9-6E9F94927C2E","fileName":"Belarus.json","displayName":"Belarus","isLoaded":false,"loadedDate":666804620.87699294},{"isSelected":false,"id":"8192ADD3-16D1-4118-BC7A-9CE67B7D0C04","fileName":"Belgium.json","displayName":"Belgium","isLoaded":false,"loadedDate":666804620.88924301},{"isSelected":false,"id":"ED10D153-EBC7-407A-9074-8F00BBA6503C","fileName":"Belize.json","displayName":"Belize","isLoaded":false,"loadedDate":666804620.90024602},{"isSelected":false,"id":"03C9DE27-B7F3-4ECB-970A-CBCFFF6B426F","fileName":"Benin.json","displayName":"Benin","isLoaded":false,"loadedDate":666804620.91004896},{"isSelected":false,"id":"304BE00A-CB50-43F2-94CF-BA513C09B1CE","fileName":"Bhutan.json","displayName":"Bhutan","isLoaded":false,"loadedDate":666804620.91852796},{"isSelected":false,"id":"71BCE837-2058-465F-A979-4FABC0406FCC","fileName":"Bolivia.json","displayName":"Bolivia","isLoaded":false,"loadedDate":666804620.92790604},{"isSelected":false,"id":"BC87B452-8CD9-4E0F-9225-034FCF975F8B","fileName":"Bosnia and Herzegovina.json","displayName":"Bosnia and Herzegovina","isLoaded":false,"loadedDate":666804620.93673301},{"isSelected":false,"id":"6A83E510-72BA-473A-AC99-3435BA972313","fileName":"Botswana.json","displayName":"Botswana","isLoaded":false,"loadedDate":666804620.94595802},{"isSelected":false,"id":"42D067F0-E2D3-401D-BD90-6E7DF4699C35","fileName":"Brazil.json","displayName":"Brazil","isLoaded":false,"loadedDate":666804620.95664406},{"isSelected":false,"id":"73773B7A-E32C-450E-9F49-1CBF3493E0DE","fileName":"Brunei.json","displayName":"Brunei","isLoaded":false,"loadedDate":666804620.96553004},{"isSelected":false,"id":"8A402213-3530-4F28-AEBC-71003F91D701","fileName":"Bulgaria.json","displayName":"Bulgaria","isLoaded":false,"loadedDate":666804620.97438395},{"isSelected":false,"id":"C7FEA518-E756-48B9-B87B-4AE932637D7C","fileName":"Burkina Faso.json","displayName":"Burkina Faso","isLoaded":false,"loadedDate":666804620.98298097},{"isSelected":false,"id":"96C62384-A090-4A2C-A017-BF63D4678688","fileName":"Burma.json","displayName":"Burma","isLoaded":false,"loadedDate":666804620.99217796},{"isSelected":false,"id":"8BD28B06-FD53-4527-98AB-F72364C65E6E","fileName":"Burundi.json","displayName":"Burundi","isLoaded":false,"loadedDate":666804621.00148594},{"isSelected":false,"id":"0BE41111-C6D0-4CDB-9CB5-1DE6C9E3EE4B","fileName":"Cabo Verde.json","displayName":"Cabo Verde","isLoaded":false,"loadedDate":666804621.01185799},{"isSelected":false,"id":"46F400CD-D652-4B1E-84D9-B8CADD6F625E","fileName":"Cambodia.json","displayName":"Cambodia","isLoaded":false,"loadedDate":666804621.02112198},{"isSelected":false,"id":"F5C30AC7-2AE1-4F57-A10D-0A76DF1C42B3","fileName":"Cameroon.json","displayName":"Cameroon","isLoaded":false,"loadedDate":666804621.02987397},{"isSelected":false,"id":"8C0C3A00-F587-423F-A252-358CA30C37BF","fileName":"Canada - Alberta.json","displayName":"Canada - Alberta","isLoaded":false,"loadedDate":666804621.04019701},{"isSelected":false,"id":"3D4589D5-CB27-4747-AD7C-CA4CCD095004","fileName":"Canada - British Columbia.json","displayName":"Canada - British Columbia","isLoaded":false,"loadedDate":666804621.04917204},{"isSelected":false,"id":"5807B6BC-CE62-4F9F-91C6-8098EC3CC520","fileName":"Canada - Diamond Princess.json","displayName":"Canada - Diamond Princess","isLoaded":false,"loadedDate":666804621.05783904},{"isSelected":false,"id":"11AE9B9F-935B-44FE-8BF0-E75D1ACB2F52","fileName":"Canada - Grand Princess.json","displayName":"Canada - Grand Princess","isLoaded":false,"loadedDate":666804621.06684196},{"isSelected":false,"id":"1078AAB4-94E7-4257-AC07-A174927A3CA0","fileName":"Canada - Manitoba.json","displayName":"Canada - Manitoba","isLoaded":false,"loadedDate":666804621.07495606},{"isSelected":false,"id":"FAD667CF-3075-4C72-84C8-2BF3FAEDC9E7","fileName":"Canada - New Brunswick.json","displayName":"Canada - New Brunswick","isLoaded":false,"loadedDate":666804621.08822703},{"isSelected":false,"id":"DBCEE8D9-128D-452E-A8DD-12C4DAE57AAF","fileName":"Canada - Newfoundland and Labrador.json","displayName":"Canada - Newfoundland and Labrador","isLoaded":false,"loadedDate":666804621.09652996},{"isSelected":false,"id":"C8B17B19-3539-489E-BAD6-11420E6D7860","fileName":"Canada - Northwest Territories.json","displayName":"Canada - Northwest Territories","isLoaded":false,"loadedDate":666804621.10484898},{"isSelected":false,"id":"F5A0FAA7-1C51-4388-BB16-7BA1AAA088DD","fileName":"Canada - Nova Scotia.json","displayName":"Canada - Nova Scotia","isLoaded":false,"loadedDate":666804621.11667395},{"isSelected":false,"id":"C765583B-8484-4EC0-9819-80E3ACAD2AAA","fileName":"Canada - Nunavut.json","displayName":"Canada - Nunavut","isLoaded":false,"loadedDate":666804621.12846196},{"isSelected":false,"id":"D4309383-3A40-407A-BDBB-BE1676820B44","fileName":"Canada - Ontario.json","displayName":"Canada - Ontario","isLoaded":false,"loadedDate":666804621.13722098},{"isSelected":false,"id":"16516F70-7CE3-4D88-AA1E-54C8FC91C178","fileName":"Canada - Prince Edward Island.json","displayName":"Canada - Prince Edward Island","isLoaded":false,"loadedDate":666804621.14584506},{"isSelected":false,"id":"534CECD2-0201-4459-AC32-A4BED07FF27A","fileName":"Canada - Quebec.json","displayName":"Canada - Quebec","isLoaded":false,"loadedDate":666804621.15708399},{"isSelected":false,"id":"C2A6113E-E062-438F-AE56-AF888AFBA4F6","fileName":"Canada - Repatriated Travellers.json","displayName":"Canada - Repatriated Travellers","isLoaded":false,"loadedDate":666804621.17013395},{"isSelected":false,"id":"92EFEFAF-8065-4B21-88B5-F2484EDAF04C","fileName":"Canada - Saskatchewan.json","displayName":"Canada - Saskatchewan","isLoaded":false,"loadedDate":666804621.178473},{"isSelected":false,"id":"F7DBBDA2-1FF6-402C-92C1-D40E35DCE303","fileName":"Canada - Yukon.json","displayName":"Canada - Yukon","isLoaded":false,"loadedDate":666804621.18915296},{"isSelected":false,"id":"20EE7A14-783B-4058-B807-6CE8B0E21EFC","fileName":"Central African Republic.json","displayName":"Central African Republic","isLoaded":false,"loadedDate":666804621.20445502},{"isSelected":false,"id":"116D2D94-4098-4744-A021-4F0A35D62C37","fileName":"Chad.json","displayName":"Chad","isLoaded":false,"loadedDate":666804621.21823096},{"isSelected":false,"id":"7F0E7ED2-42E7-4580-896F-78D336322BA4","fileName":"Chile.json","displayName":"Chile","isLoaded":false,"loadedDate":666804621.23115003},{"isSelected":false,"id":"944A1184-C1B3-415C-B90C-E1018ACFCA0F","fileName":"China - Anhui.json","displayName":"China - Anhui","isLoaded":false,"loadedDate":666804621.24463904},{"isSelected":false,"id":"3E6B9012-832D-49BE-AC1A-F87C90FD1C59","fileName":"China - Beijing.json","displayName":"China - Beijing","isLoaded":false,"loadedDate":666804621.26131201},{"isSelected":false,"id":"6D42489D-7D71-43C5-ADAB-A915E6034AF8","fileName":"China - Chongqing.json","displayName":"China - Chongqing","isLoaded":false,"loadedDate":666804621.27333605},{"isSelected":false,"id":"AC9441AB-D5AE-43BA-9665-4F27AC669625","fileName":"China - Fujian.json","displayName":"China - Fujian","isLoaded":false,"loadedDate":666804621.28408504},{"isSelected":false,"id":"23AA562C-9DEA-4558-8A24-9CDF5B53E272","fileName":"China - Gansu.json","displayName":"China - Gansu","isLoaded":false,"loadedDate":666804621.29304099},{"isSelected":false,"id":"02A5DE8F-3F7E-4799-BE7C-E072748D184F","fileName":"China - Guangdong.json","displayName":"China - Guangdong","isLoaded":false,"loadedDate":666804621.30242801},{"isSelected":false,"id":"164D5FC3-70A7-4ACA-9731-3CC25D0BA774","fileName":"China - Guangxi.json","displayName":"China - Guangxi","isLoaded":false,"loadedDate":666804621.31068695},{"isSelected":false,"id":"E02DA9B2-484E-433B-BFD6-3DC992B3F7FB","fileName":"China - Guizhou.json","displayName":"China - Guizhou","isLoaded":false,"loadedDate":666804621.31944394},{"isSelected":false,"id":"86731A38-33B4-47AA-A0A8-CC9EF1B8F108","fileName":"China - Hainan.json","displayName":"China - Hainan","isLoaded":false,"loadedDate":666804621.32803798},{"isSelected":false,"id":"522DEB85-8681-4516-B2EB-AD78CBAA5169","fileName":"China - Hebei.json","displayName":"China - Hebei","isLoaded":false,"loadedDate":666804621.337093},{"isSelected":false,"id":"AEFE8BD2-6D33-4995-A0A3-6C80AA325582","fileName":"China - Heilongjiang.json","displayName":"China - Heilongjiang","isLoaded":false,"loadedDate":666804621.34557199},{"isSelected":false,"id":"55139ECA-2356-4DA5-A6AE-E03F269F4C1B","fileName":"China - Henan.json","displayName":"China - Henan","isLoaded":false,"loadedDate":666804621.35443699},{"isSelected":false,"id":"37C1040C-A5A8-495C-AA58-16C1D4464893","fileName":"China - Hong Kong.json","displayName":"China - Hong Kong","isLoaded":false,"loadedDate":666804621.36478996},{"isSelected":false,"id":"EFF935EA-1384-4CF1-8F0D-58C3E2C90664","fileName":"China - Hubei.json","displayName":"China - Hubei","isLoaded":false,"loadedDate":666804621.376688},{"isSelected":false,"id":"A56BD7AC-BABC-42D4-947D-C780D7002A31","fileName":"China - Hunan.json","displayName":"China - Hunan","isLoaded":false,"loadedDate":666804621.38582301},{"isSelected":false,"id":"545BFCBA-6CF7-441B-B4B8-5885174405A3","fileName":"China - Inner Mongolia.json","displayName":"China - Inner Mongolia","isLoaded":false,"loadedDate":666804621.40104496},{"isSelected":false,"id":"4E4F593C-3CBB-438A-9858-B09B01AB1169","fileName":"China - Jiangsu.json","displayName":"China - Jiangsu","isLoaded":false,"loadedDate":666804621.40903795},{"isSelected":false,"id":"A9633747-A4DA-4C01-B987-60DA4EAD920E","fileName":"China - Jiangxi.json","displayName":"China - Jiangxi","isLoaded":false,"loadedDate":666804621.41720104},{"isSelected":false,"id":"377355A6-92D6-4667-98A7-B4592FA48844","fileName":"China - Jilin.json","displayName":"China - Jilin","isLoaded":false,"loadedDate":666804621.42574799},{"isSelected":false,"id":"2AC7872A-64E2-4CBE-AB8F-639C9F8F6828","fileName":"China - Liaoning.json","displayName":"China - Liaoning","isLoaded":false,"loadedDate":666804621.43417704},{"isSelected":false,"id":"59B1B73B-2881-4F76-8FD7-828F1066AB81","fileName":"China - Macau.json","displayName":"China - Macau","isLoaded":false,"loadedDate":666804621.44255495},{"isSelected":false,"id":"76366232-47BF-4EAF-BF23-5157D15631DC","fileName":"China - Ningxia.json","displayName":"China - Ningxia","isLoaded":false,"loadedDate":666804621.44993103},{"isSelected":false,"id":"73B4B719-6220-48A4-B7BF-3A1759543DAF","fileName":"China - Qinghai.json","displayName":"China - Qinghai","isLoaded":false,"loadedDate":666804621.45925105},{"isSelected":false,"id":"A6A2BB08-B6BF-4C31-A8BA-36A8CA5F5B10","fileName":"China - Shaanxi.json","displayName":"China - Shaanxi","isLoaded":false,"loadedDate":666804621.46769595},{"isSelected":false,"id":"B2E2CCCB-DC5A-4949-B809-1A0D44A0465E","fileName":"China - Shandong.json","displayName":"China - Shandong","isLoaded":false,"loadedDate":666804621.47474205},{"isSelected":false,"id":"D0C338F8-BC8B-4712-A207-B72B987EE5F3","fileName":"China - Shanghai.json","displayName":"China - Shanghai","isLoaded":false,"loadedDate":666804621.48332798},{"isSelected":false,"id":"2D2AACA6-59ED-4DE8-B4AD-5096D28B1A76","fileName":"China - Shanxi.json","displayName":"China - Shanxi","isLoaded":false,"loadedDate":666804621.49183297},{"isSelected":false,"id":"B4CB3477-969B-462C-A291-BC02BC4577AF","fileName":"China - Sichuan.json","displayName":"China - Sichuan","isLoaded":false,"loadedDate":666804621.50072002},{"isSelected":false,"id":"1B4CB574-079F-4524-AE4C-77FF67C8B586","fileName":"China - Tianjin.json","displayName":"China - Tianjin","isLoaded":false,"loadedDate":666804621.50985396},{"isSelected":false,"id":"19A04BC5-28D9-4185-9858-76B6D139EA24","fileName":"China - Tibet.json","displayName":"China - Tibet","isLoaded":false,"loadedDate":666804621.51851296},{"isSelected":false,"id":"CB18751E-57F7-4509-9D45-33A635237F00","fileName":"China - Unknown.json","displayName":"China - Unknown","isLoaded":false,"loadedDate":666804621.52723205},{"isSelected":false,"id":"409EA0AD-D42D-459D-8416-E744ECC4BB8A","fileName":"China - Xinjiang.json","displayName":"China - Xinjiang","isLoaded":false,"loadedDate":666804621.53601205},{"isSelected":false,"id":"E6876282-809E-4DCF-A66D-62D38944DDC5","fileName":"China - Yunnan.json","displayName":"China - Yunnan","isLoaded":false,"loadedDate":666804621.54497099},{"isSelected":false,"id":"0E59B790-F6B6-419D-8C60-4AF856505EDD","fileName":"China - Zhejiang.json","displayName":"China - Zhejiang","isLoaded":false,"loadedDate":666804621.55447102},{"isSelected":false,"id":"8FC0C3F8-0151-460B-A5A9-6D8F07F86F6A","fileName":"Colombia.json","displayName":"Colombia","isLoaded":false,"loadedDate":666804621.56247795},{"isSelected":false,"id":"ACDD0295-D457-4746-B70C-905FE1059464","fileName":"Comoros.json","displayName":"Comoros","isLoaded":false,"loadedDate":666804621.57071304},{"isSelected":false,"id":"BCDAB560-7C86-49E7-8351-7881F3CE54A0","fileName":"Congo (Brazzaville).json","displayName":"Congo (Brazzaville)","isLoaded":false,"loadedDate":666804621.57861197},{"isSelected":false,"id":"397370E6-98E8-4071-82C5-246C469614B1","fileName":"Congo (Kinshasa).json","displayName":"Congo (Kinshasa)","isLoaded":false,"loadedDate":666804621.58744395},{"isSelected":false,"id":"2AD99F9B-2A07-4CEB-A2E2-2A96443E3BC8","fileName":"Costa Rica.json","displayName":"Costa Rica","isLoaded":false,"loadedDate":666804621.59599698},{"isSelected":false,"id":"3AAC6381-FCCD-4A2B-A502-139D8E0C66E7","fileName":"Cote d'Ivoire.json","displayName":"Cote d'Ivoire","isLoaded":false,"loadedDate":666804621.60505605},{"isSelected":false,"id":"960B5B2C-5EAA-4EC4-806F-0C850D7ECEBD","fileName":"Croatia.json","displayName":"Croatia","isLoaded":false,"loadedDate":666804621.61375594},{"isSelected":false,"id":"E97C401C-AF61-429A-81DF-B90C0D5098ED","fileName":"Cuba.json","displayName":"Cuba","isLoaded":false,"loadedDate":666804621.62255299},{"isSelected":false,"id":"B4073616-9EB3-4720-998C-EFF5CD74F5FA","fileName":"Cyprus.json","displayName":"Cyprus","isLoaded":false,"loadedDate":666804621.63128698},{"isSelected":false,"id":"1E2B319A-B431-4BFC-B9D4-872BD2656BCB","fileName":"Czechia.json","displayName":"Czechia","isLoaded":false,"loadedDate":666804621.64250004},{"isSelected":false,"id":"9B3D15B8-2156-4EB9-BF14-743D255A0549","fileName":"Denmark.json","displayName":"Denmark","isLoaded":false,"loadedDate":666804621.67012405},{"isSelected":false,"id":"752EA9BB-3323-4512-9968-A68BD77F15F2","fileName":"Denmark - Faroe Islands.json","displayName":"Denmark - Faroe Islands","isLoaded":false,"loadedDate":666804621.65123606},{"isSelected":false,"id":"504F266C-85E3-4503-98F0-7ACA63845856","fileName":"Denmark - Greenland.json","displayName":"Denmark - Greenland","isLoaded":false,"loadedDate":666804621.66126096},{"isSelected":false,"id":"3C6EF8C0-F49E-4580-ADE4-6D358BC403F2","fileName":"Diamond Princess.json","displayName":"Diamond Princess","isLoaded":false,"loadedDate":666804621.67854095},{"isSelected":false,"id":"5A0BF828-7312-426E-B2F7-52C49200A3E9","fileName":"Djibouti.json","displayName":"Djibouti","isLoaded":false,"loadedDate":666804621.68670595},{"isSelected":false,"id":"C1E3FD60-8A46-401A-AD57-253C0DB9A594","fileName":"Dominica.json","displayName":"Dominica","isLoaded":false,"loadedDate":666804621.694942},{"isSelected":false,"id":"077A1339-8DFF-438D-9570-0ABFAC39E433","fileName":"Dominican Republic.json","displayName":"Dominican Republic","isLoaded":false,"loadedDate":666804621.70402098},{"isSelected":false,"id":"C30A2C67-152A-47FD-B7F6-7835363FB1F7","fileName":"Ecuador.json","displayName":"Ecuador","isLoaded":false,"loadedDate":666804621.71300101},{"isSelected":false,"id":"C89820C3-F0E7-413C-8D33-361A7A4E6B8D","fileName":"Egypt.json","displayName":"Egypt","isLoaded":false,"loadedDate":666804621.72280705},{"isSelected":false,"id":"C9A137A7-E077-42EE-A0D0-57FA3FF6D9E5","fileName":"El Salvador.json","displayName":"El Salvador","isLoaded":false,"loadedDate":666804621.73213005},{"isSelected":false,"id":"F52BFA9A-81C8-461C-B106-E3C639AFBC50","fileName":"Equatorial Guinea.json","displayName":"Equatorial Guinea","isLoaded":false,"loadedDate":666804621.74111497},{"isSelected":false,"id":"BB739F03-0DEC-432D-86F7-4902662D7737","fileName":"Eritrea.json","displayName":"Eritrea","isLoaded":false,"loadedDate":666804621.75059104},{"isSelected":false,"id":"0E80EFA6-83DC-44BF-8AB9-9CF9FCA5B73D","fileName":"Estonia.json","displayName":"Estonia","isLoaded":false,"loadedDate":666804621.75914598},{"isSelected":false,"id":"066D9625-1AE4-400A-8A18-EB070F7EE706","fileName":"Eswatini.json","displayName":"Eswatini","isLoaded":false,"loadedDate":666804621.76750898},{"isSelected":false,"id":"4CF775E0-5152-4C3A-BE93-80166C273220","fileName":"Ethiopia.json","displayName":"Ethiopia","isLoaded":false,"loadedDate":666804621.77624297},{"isSelected":false,"id":"904EA42D-584D-4BC5-9FEF-F10D72F52324","fileName":"Fiji.json","displayName":"Fiji","isLoaded":false,"loadedDate":666804621.784356},{"isSelected":false,"id":"5CE768D2-5C91-49D0-BE39-D5A2304BE283","fileName":"Finland.json","displayName":"Finland","isLoaded":false,"loadedDate":666804621.79293501},{"isSelected":false,"id":"035D60FF-BF7F-446E-AE5F-67238B408E24","fileName":"France.json","displayName":"France","isLoaded":false,"loadedDate":666804621.92037106},{"isSelected":false,"id":"55BA5E54-A88B-4D55-B823-B7F22D49B4E6","fileName":"France - French Guiana.json","displayName":"France - French Guiana","isLoaded":false,"loadedDate":666804621.80205297},{"isSelected":false,"id":"72CE3CF8-A691-4047-9B2D-5D2F7A2B54A0","fileName":"France - French Polynesia.json","displayName":"France - French Polynesia","isLoaded":false,"loadedDate":666804621.811041},{"isSelected":false,"id":"623F2F57-0B2A-424D-B8CA-2AA0E04F59A9","fileName":"France - Guadeloupe.json","displayName":"France - Guadeloupe","isLoaded":false,"loadedDate":666804621.82011104},{"isSelected":false,"id":"DE494F4A-1659-4ACD-AF82-D88631D1AE51","fileName":"France - Martinique.json","displayName":"France - Martinique","isLoaded":false,"loadedDate":666804621.83000398},{"isSelected":false,"id":"37373C72-A387-456D-9F9E-FAA679E4632C","fileName":"France - Mayotte.json","displayName":"France - Mayotte","isLoaded":false,"loadedDate":666804621.84009302},{"isSelected":false,"id":"582D20D6-28D8-4D3A-B611-27855FCD53A1","fileName":"France - New Caledonia.json","displayName":"France - New Caledonia","isLoaded":false,"loadedDate":666804621.84904099},{"isSelected":false,"id":"7971ADF0-388D-4198-AD1C-536647981957","fileName":"France - Reunion.json","displayName":"France - Reunion","isLoaded":false,"loadedDate":666804621.85808897},{"isSelected":false,"id":"8B31F7E6-2402-4681-8D56-5A991076EFF1","fileName":"France - Saint Barthelemy.json","displayName":"France - Saint Barthelemy","isLoaded":false,"loadedDate":666804621.867226},{"isSelected":false,"id":"BFECE903-B958-4FA9-9A30-3B47FF37A4A9","fileName":"France - Saint Pierre and Miquelon.json","displayName":"France - Saint Pierre and Miquelon","isLoaded":false,"loadedDate":666804621.87776804},{"isSelected":false,"id":"83A084A0-3D02-4642-A761-7EB8F53783E5","fileName":"France - St Martin.json","displayName":"France - St Martin","isLoaded":false,"loadedDate":666804621.89531004},{"isSelected":false,"id":"9CB966EC-6DB7-4532-9AD2-D42B796AA356","fileName":"France - Wallis and Futuna.json","displayName":"France - Wallis and Futuna","isLoaded":false,"loadedDate":666804621.90546298},{"isSelected":false,"id":"05E3A0F2-AC74-463D-8775-5FF6AFEBD78C","fileName":"Gabon.json","displayName":"Gabon","isLoaded":false,"loadedDate":666804621.93331301},{"isSelected":false,"id":"112EE66B-967E-44B4-A1D2-14D4A857662D","fileName":"Gambia.json","displayName":"Gambia","isLoaded":false,"loadedDate":666804621.94599104},{"isSelected":false,"id":"A4D65E54-84AE-4A4A-A584-B20C17662DF7","fileName":"Georgia.json","displayName":"Georgia","isLoaded":false,"loadedDate":666804621.95897305},{"isSelected":false,"id":"47D124D1-C939-4523-8EAD-2EEE9169C476","fileName":"Germany.json","displayName":"Germany","isLoaded":false,"loadedDate":666804621.977139},{"isSelected":false,"id":"C661E40A-8125-4C1B-83E7-B8238E971EF8","fileName":"Ghana.json","displayName":"Ghana","isLoaded":false,"loadedDate":666804621.99115801},{"isSelected":false,"id":"B73F7510-4200-4B42-8604-EB700894D85D","fileName":"Greece.json","displayName":"Greece","isLoaded":false,"loadedDate":666804622.00497997},{"isSelected":false,"id":"C72021DA-2943-4FD7-BE02-C6E1F075F42A","fileName":"Grenada.json","displayName":"Grenada","isLoaded":false,"loadedDate":666804622.01459002},{"isSelected":false,"id":"817ED3E4-025D-42C5-8791-26B00D80A0D6","fileName":"Guatemala.json","displayName":"Guatemala","isLoaded":false,"loadedDate":666804622.02763605},{"isSelected":false,"id":"A3794538-953C-42A4-9188-5992AF82C8CC","fileName":"Guinea.json","displayName":"Guinea","isLoaded":false,"loadedDate":666804622.03605103},{"isSelected":false,"id":"7D9871D0-6EDA-4934-BC47-9699E7C78DC9","fileName":"Guinea-Bissau.json","displayName":"Guinea-Bissau","isLoaded":false,"loadedDate":666804622.04456794},{"isSelected":false,"id":"DC0EAA25-E16A-4C49-B4C3-26376A18FDCE","fileName":"Guyana.json","displayName":"Guyana","isLoaded":false,"loadedDate":666804622.053316},{"isSelected":false,"id":"09A8145C-AC21-427D-B914-6E5C4A3F1BDB","fileName":"Haiti.json","displayName":"Haiti","isLoaded":false,"loadedDate":666804622.06179595},{"isSelected":false,"id":"AE045F49-D869-43B7-9220-F87DCDCC582E","fileName":"Holy See.json","displayName":"Holy See","isLoaded":false,"loadedDate":666804622.07052195},{"isSelected":false,"id":"6C33CDF9-5638-4144-93CA-015A0DCB36FA","fileName":"Honduras.json","displayName":"Honduras","isLoaded":false,"loadedDate":666804622.07886505},{"isSelected":false,"id":"15446DE6-1555-4DEA-A466-7CD1C1E45180","fileName":"Hungary.json","displayName":"Hungary","isLoaded":false,"loadedDate":666804622.08751798},{"isSelected":false,"id":"F02E4E06-31BD-4DEF-A311-055F2AB95391","fileName":"Iceland.json","displayName":"Iceland","isLoaded":false,"loadedDate":666804622.09611905},{"isSelected":false,"id":"3EB0503C-8DE6-4312-BE8A-33B1D61C631A","fileName":"India.json","displayName":"India","isLoaded":false,"loadedDate":666804622.10496294},{"isSelected":false,"id":"BE9A4711-9305-45AD-9127-95120B4126F1","fileName":"Indonesia.json","displayName":"Indonesia","isLoaded":false,"loadedDate":666804622.11391103},{"isSelected":false,"id":"4C8C126B-77D3-4D20-ABC7-B881F4375620","fileName":"Iran.json","displayName":"Iran","isLoaded":false,"loadedDate":666804622.13619101},{"isSelected":false,"id":"9E17A604-6FCE-4D63-8A50-9D4D6E20212C","fileName":"Iraq.json","displayName":"Iraq","isLoaded":false,"loadedDate":666804622.14576006},{"isSelected":false,"id":"90D916A9-95E0-4374-9C80-944022FBD5B2","fileName":"Ireland.json","displayName":"Ireland","isLoaded":false,"loadedDate":666804622.15478599},{"isSelected":false,"id":"1F367703-D7EF-46B0-B8A2-733FE538F488","fileName":"Israel.json","displayName":"Israel","isLoaded":false,"loadedDate":666804622.163589},{"isSelected":false,"id":"841D2DFE-C004-45D4-9E04-28F064801627","fileName":"Italy.json","displayName":"Italy","isLoaded":false,"loadedDate":666804622.17251098},{"isSelected":false,"id":"FD39264E-2943-42F3-8F93-0BD37D6ABC85","fileName":"Italy - Abruzzo.json","displayName":"Italy - Abruzzo","isLoaded":false,"loadedDate":666804620.55839205},{"isSelected":false,"id":"EE142F10-48E9-4865-95FF-9AAFBC1E5017","fileName":"Italy - Basilicata.json","displayName":"Italy - Basilicata","isLoaded":false,"loadedDate":666804620.65061498},{"isSelected":false,"id":"1A43F9E6-4AA4-4964-8800-8B7284023F57","fileName":"Italy - Calabria.json","displayName":"Italy - Calabria","isLoaded":false,"loadedDate":666804620.62348998},{"isSelected":false,"id":"328F7223-6891-4B83-9EAE-C1D8EB0D210B","fileName":"Italy - Campania.json","displayName":"Italy - Campania","isLoaded":false,"loadedDate":666804620.49896598},{"isSelected":false,"id":"490A1AD2-CD26-414C-8C12-5D6CDF988073","fileName":"Italy - Emilia-Romagna.json","displayName":"Italy - Emilia-Romagna","isLoaded":false,"loadedDate":666804620.65741801},{"isSelected":false,"id":"0C0C28FC-BC91-4B9E-86DD-C3D3B83C6F64","fileName":"Italy - Friuli Venezia Giulia.json","displayName":"Italy - Friuli Venezia Giulia","isLoaded":false,"loadedDate":666804620.63709104},{"isSelected":false,"id":"37B8008B-EB63-45EF-92B3-F2E6B3E9CBD3","fileName":"Italy - Lazio.json","displayName":"Italy - Lazio","isLoaded":false,"loadedDate":666804620.644045},{"isSelected":false,"id":"C7287B14-1781-4301-A05A-19E0D91E6557","fileName":"Italy - Liguria.json","displayName":"Italy - Liguria","isLoaded":false,"loadedDate":666804620.60303402},{"isSelected":false,"id":"4C4C4EB0-111F-41DB-9AB3-3DF7AE76941E","fileName":"Italy - Lombardia.json","displayName":"Italy - Lombardia","isLoaded":false,"loadedDate":666804620.50967097},{"isSelected":false,"id":"45372A39-BDFA-49B9-A6CD-2485AAFA4903","fileName":"Italy - Marche.json","displayName":"Italy - Marche","isLoaded":false,"loadedDate":666804620.61679494},{"isSelected":false,"id":"1D5B00F4-6507-4566-96E2-97AACFE6FA0D","fileName":"Italy - Molise.json","displayName":"Italy - Molise","isLoaded":false,"loadedDate":666804620.56824398},{"isSelected":false,"id":"01B6D5D6-B19F-4A24-B0F6-1841EDDDF06C","fileName":"Italy - P.A. Bolzano.json","displayName":"Italy - P.A. Bolzano","isLoaded":false,"loadedDate":666804620.52037299},{"isSelected":false,"id":"05604DFF-264C-4381-B945-A496528CE354","fileName":"Italy - P.A. Trento.json","displayName":"Italy - P.A. Trento","isLoaded":false,"loadedDate":666804620.55030596},{"isSelected":false,"id":"82AF3826-C977-47B2-821A-A0EBC70C6830","fileName":"Italy - Piemonte.json","displayName":"Italy - Piemonte","isLoaded":false,"loadedDate":666804620.57595599},{"isSelected":false,"id":"F56B2082-1241-4CD8-A1FC-6A829E6B8CF1","fileName":"Italy - Puglia.json","displayName":"Italy - Puglia","isLoaded":false,"loadedDate":666804620.53100502},{"isSelected":false,"id":"36BC0A0D-EB60-4786-9A42-C0D1D7493C6C","fileName":"Italy - Sardegna.json","displayName":"Italy - Sardegna","isLoaded":false,"loadedDate":666804620.582528},{"isSelected":false,"id":"789E8801-5B1C-45D8-88F1-25C91E0CEA8C","fileName":"Italy - Sicilia.json","displayName":"Italy - Sicilia","isLoaded":false,"loadedDate":666804620.59625196},{"isSelected":false,"id":"703CC609-A90C-419A-9065-27A559848F1A","fileName":"Italy - Toscana.json","displayName":"Italy - Toscana","isLoaded":false,"loadedDate":666804620.60992801},{"isSelected":false,"id":"B39E6C1F-1455-437D-B7CD-5DFF9EB611D2","fileName":"Italy - Umbria.json","displayName":"Italy - Umbria","isLoaded":false,"loadedDate":666804620.58935499},{"isSelected":false,"id":"FAF008FF-0B62-42EF-8C0F-6BE4A0412AEA","fileName":"Italy - Valle d'Aosta.json","displayName":"Italy - Valle d'Aosta","isLoaded":false,"loadedDate":666804620.54152703},{"isSelected":false,"id":"982C4531-6294-4534-A5D8-AEC6E9CC9D7D","fileName":"Italy - Veneto.json","displayName":"Italy - Veneto","isLoaded":false,"loadedDate":666804620.63040805},{"isSelected":false,"id":"D93D8F52-FEF3-4976-85C8-CF9ACB462B6F","fileName":"Jamaica.json","displayName":"Jamaica","isLoaded":false,"loadedDate":666804622.18185902},{"isSelected":false,"id":"70998A5B-A925-4EBB-A346-5FA48CB1810D","fileName":"Japan.json","displayName":"Japan","isLoaded":false,"loadedDate":666804622.19101405},{"isSelected":false,"id":"8133DE0C-6C93-49B4-9CA1-9AB0B7E167D2","fileName":"Jordan.json","displayName":"Jordan","isLoaded":false,"loadedDate":666804622.202932},{"isSelected":false,"id":"13544F93-C4F9-4B4E-B641-373C691E80DB","fileName":"Kazakhstan.json","displayName":"Kazakhstan","isLoaded":false,"loadedDate":666804622.21159697},{"isSelected":false,"id":"78AE3E69-3272-4752-B5FB-3FB0214B3C0A","fileName":"Kenya.json","displayName":"Kenya","isLoaded":false,"loadedDate":666804622.22053599},{"isSelected":false,"id":"6ACC1C3B-410C-4F53-931C-9802E666A120","fileName":"Kiribati.json","displayName":"Kiribati","isLoaded":false,"loadedDate":666804622.22873402},{"isSelected":false,"id":"C9D0B93D-AE9F-4BA2-B685-F1D20B1F92C1","fileName":"Korea, South.json","displayName":"Korea, South","isLoaded":false,"loadedDate":666804622.23789203},{"isSelected":false,"id":"4CD490E9-BAF6-47EA-AADF-54E3129D5A52","fileName":"Kosovo.json","displayName":"Kosovo","isLoaded":false,"loadedDate":666804622.24612999},{"isSelected":false,"id":"83090D8F-DB27-469D-87A5-6A9FF66DD9A7","fileName":"Kuwait.json","displayName":"Kuwait","isLoaded":false,"loadedDate":666804622.25506997},{"isSelected":false,"id":"9B3FD899-EAC6-45AC-9A39-73FC6330CA30","fileName":"Kyrgyzstan.json","displayName":"Kyrgyzstan","isLoaded":false,"loadedDate":666804622.26365697},{"isSelected":false,"id":"0053072F-1885-4FA1-806D-0644F5AB99E5","fileName":"Laos.json","displayName":"Laos","isLoaded":false,"loadedDate":666804622.27251899},{"isSelected":false,"id":"359AB44A-49DC-459D-A2A0-0E3A99AF90C8","fileName":"Latvia.json","displayName":"Latvia","isLoaded":false,"loadedDate":666804622.28149402},{"isSelected":false,"id":"607F5063-7624-4ADC-8CB4-17B029EB61C8","fileName":"Lebanon.json","displayName":"Lebanon","isLoaded":false,"loadedDate":666804622.29006398},{"isSelected":false,"id":"165941A0-4DFE-4428-990C-83D0ABA7D5A6","fileName":"Lesotho.json","displayName":"Lesotho","isLoaded":false,"loadedDate":666804622.29909801},{"isSelected":false,"id":"E2DED53E-9F47-48E3-87E8-10FDD46E34AA","fileName":"Liberia.json","displayName":"Liberia","isLoaded":false,"loadedDate":666804622.308442},{"isSelected":false,"id":"B8C12FC7-954A-46A7-AD58-7D08C049513E","fileName":"Libya.json","displayName":"Libya","isLoaded":false,"loadedDate":666804622.31720495},{"isSelected":false,"id":"F3693AC5-4848-4319-93C8-7CDC70D8B5B1","fileName":"Liechtenstein.json","displayName":"Liechtenstein","isLoaded":false,"loadedDate":666804622.32671905},{"isSelected":false,"id":"5518D140-5E4A-403F-9465-4E10B83498C4","fileName":"Lithuania.json","displayName":"Lithuania","isLoaded":false,"loadedDate":666804622.33517802},{"isSelected":false,"id":"7A787BB4-DF14-455A-B628-DED9C7C432A2","fileName":"Luxembourg.json","displayName":"Luxembourg","isLoaded":false,"loadedDate":666804622.34489501},{"isSelected":false,"id":"E5001FE1-E160-44CD-ABF4-EFE453EC0ABF","fileName":"MS Zaandam.json","displayName":"MS Zaandam","isLoaded":false,"loadedDate":666804622.35328197},{"isSelected":false,"id":"566B9737-59FC-44FC-BDFC-8BA1C6D772C0","fileName":"Madagascar.json","displayName":"Madagascar","isLoaded":false,"loadedDate":666804622.36162996},{"isSelected":false,"id":"3FFC4FD0-4B2A-49A5-9798-E22719BE6BE8","fileName":"Malawi.json","displayName":"Malawi","isLoaded":false,"loadedDate":666804622.37039006},{"isSelected":false,"id":"10EEA83A-5F1F-4961-8EE9-6B4B644E2C6E","fileName":"Malaysia.json","displayName":"Malaysia","isLoaded":false,"loadedDate":666804622.37864697},{"isSelected":false,"id":"3FDAFB22-F086-42AE-9000-04BCC9020339","fileName":"Maldives.json","displayName":"Maldives","isLoaded":false,"loadedDate":666804622.38754106},{"isSelected":false,"id":"1DAAD655-4138-41CD-A568-A8B231F9B371","fileName":"Mali.json","displayName":"Mali","isLoaded":false,"loadedDate":666804622.395823},{"isSelected":false,"id":"B4B96A9C-EBD2-4BBB-9DB4-71D7AFCB10D4","fileName":"Malta.json","displayName":"Malta","isLoaded":false,"loadedDate":666804622.40435803},{"isSelected":false,"id":"B6C022B0-3BE1-42EE-BF56-090F24364E46","fileName":"Marshall Islands.json","displayName":"Marshall Islands","isLoaded":false,"loadedDate":666804622.414276},{"isSelected":false,"id":"BF8EDAD5-E598-43E4-BCD0-89336781997D","fileName":"Mauritania.json","displayName":"Mauritania","isLoaded":false,"loadedDate":666804622.42236197},{"isSelected":false,"id":"B1A90D58-9F56-4387-BAE7-51C39EFF18DF","fileName":"Mauritius.json","displayName":"Mauritius","isLoaded":false,"loadedDate":666804622.43069899},{"isSelected":false,"id":"00C7638F-57AC-41EB-B856-A48781CBC16E","fileName":"Mexico.json","displayName":"Mexico","isLoaded":false,"loadedDate":666804622.43962502},{"isSelected":false,"id":"15E26663-19D7-41BC-A8A4-103A140CBD5C","fileName":"Micronesia.json","displayName":"Micronesia","isLoaded":false,"loadedDate":666804622.44874096},{"isSelected":false,"id":"1C52D1B7-D073-4C90-809E-C1787FFF20C0","fileName":"Moldova.json","displayName":"Moldova","isLoaded":false,"loadedDate":666804622.45703804},{"isSelected":false,"id":"1A66C758-AEF2-4537-A870-20B51532382C","fileName":"Monaco.json","displayName":"Monaco","isLoaded":false,"loadedDate":666804622.46547401},{"isSelected":false,"id":"B44D5A44-F766-4B9C-85E3-9082040A2680","fileName":"Mongolia.json","displayName":"Mongolia","isLoaded":false,"loadedDate":666804622.474805},{"isSelected":false,"id":"AAABF3D7-EAA6-4159-9A40-36A4583D56FD","fileName":"Montenegro.json","displayName":"Montenegro","isLoaded":false,"loadedDate":666804622.48334897},{"isSelected":false,"id":"7EF94CA3-9685-4FD1-AFAB-56CFCE2C71F3","fileName":"Morocco.json","displayName":"Morocco","isLoaded":false,"loadedDate":666804622.49188602},{"isSelected":false,"id":"48B7BD5D-2D5E-4707-8DBE-B7F24D1F0A4A","fileName":"Mozambique.json","displayName":"Mozambique","isLoaded":false,"loadedDate":666804622.50022805},{"isSelected":false,"id":"12A49A2C-B553-40E5-BD94-A7247276EA66","fileName":"Namibia.json","displayName":"Namibia","isLoaded":false,"loadedDate":666804622.50837302},{"isSelected":false,"id":"BFACD273-12D9-45BD-891C-9150FAD3CB75","fileName":"Nepal.json","displayName":"Nepal","isLoaded":false,"loadedDate":666804622.51767397},{"isSelected":false,"id":"7560A97D-C31B-466E-B7C0-20FE8BEFB16E","fileName":"Netherlands.json","displayName":"Netherlands","isLoaded":false,"loadedDate":666804622.56794},{"isSelected":false,"id":"63A7D733-23E1-4131-8AD5-FD610C4524FD","fileName":"Netherlands - Aruba.json","displayName":"Netherlands - Aruba","isLoaded":false,"loadedDate":666804622.52601194},{"isSelected":false,"id":"DE6DC005-E731-442A-91D7-AB519EE28933","fileName":"Netherlands - Bonaire, Sint Eustatius and Saba.json","displayName":"Netherlands - Bonaire, Sint Eustatius and Saba","isLoaded":false,"loadedDate":666804622.53424597},{"isSelected":false,"id":"DB2ACBA6-350B-448B-AAD4-06EFD84027AA","fileName":"Netherlands - Curacao.json","displayName":"Netherlands - Curacao","isLoaded":false,"loadedDate":666804622.54912496},{"isSelected":false,"id":"4B8DB03D-FCD6-4012-83E5-CA4C36F699AC","fileName":"Netherlands - Sint Maarten.json","displayName":"Netherlands - Sint Maarten","isLoaded":false,"loadedDate":666804622.55788898},{"isSelected":false,"id":"FA617336-A5AB-410D-AEFC-52287C198043","fileName":"New Zealand.json","displayName":"New Zealand","isLoaded":false,"loadedDate":666804622.58556104},{"isSelected":false,"id":"3CC2A78E-1DB1-483F-B714-9D5C0C1CCBD4","fileName":"New Zealand - Cook Islands.json","displayName":"New Zealand - Cook Islands","isLoaded":false,"loadedDate":666804622.576985},{"isSelected":false,"id":"84175C78-A954-4722-B284-9D11BCA58150","fileName":"Nicaragua.json","displayName":"Nicaragua","isLoaded":false,"loadedDate":666804622.59413195},{"isSelected":false,"id":"77176514-0EFB-494C-BFC6-DDE7E76AF143","fileName":"Niger.json","displayName":"Niger","isLoaded":false,"loadedDate":666804622.603356},{"isSelected":false,"id":"FD3E5D6F-F669-4B4E-BA87-7ADD9F07504E","fileName":"Nigeria.json","displayName":"Nigeria","isLoaded":false,"loadedDate":666804622.61277902},{"isSelected":false,"id":"34BAF0AC-AA47-442F-8DF9-C82B24322946","fileName":"North Macedonia.json","displayName":"North Macedonia","isLoaded":false,"loadedDate":666804622.62201297},{"isSelected":false,"id":"44B355C8-ECF5-460E-8F55-DC3D140DFAF4","fileName":"Norway.json","displayName":"Norway","isLoaded":false,"loadedDate":666804622.63070905},{"isSelected":false,"id":"DC75A091-E187-4813-A86F-F748590F116C","fileName":"Oman.json","displayName":"Oman","isLoaded":false,"loadedDate":666804622.63968301},{"isSelected":false,"id":"8EF67586-3EE5-459B-892C-7D7FEA543770","fileName":"Pakistan.json","displayName":"Pakistan","isLoaded":false,"loadedDate":666804622.64943898},{"isSelected":false,"id":"B369B45A-E8F3-4EB9-97F9-C67004F12AFB","fileName":"Palau.json","displayName":"Palau","isLoaded":false,"loadedDate":666804622.65807402},{"isSelected":false,"id":"E920D997-522E-4E35-9BCE-7271EF37016F","fileName":"Panama.json","displayName":"Panama","isLoaded":false,"loadedDate":666804622.66622198},{"isSelected":false,"id":"41E04AE5-4159-4CE2-96CE-E501C1A0656F","fileName":"Papua New Guinea.json","displayName":"Papua New Guinea","isLoaded":false,"loadedDate":666804622.67587495},{"isSelected":false,"id":"D7976575-C307-479F-9BC1-007388B649AE","fileName":"Paraguay.json","displayName":"Paraguay","isLoaded":false,"loadedDate":666804622.68401098},{"isSelected":false,"id":"E8B95E57-D6B3-49B6-8FDA-C02CEB667E53","fileName":"Peru.json","displayName":"Peru","isLoaded":false,"loadedDate":666804622.70330095},{"isSelected":false,"id":"3DB3C724-B0E0-4541-895C-F27CEDA0F98A","fileName":"Philippines.json","displayName":"Philippines","isLoaded":false,"loadedDate":666804622.71193898},{"isSelected":false,"id":"46DC8784-9BD7-4A54-8F88-A08065931E17","fileName":"Poland.json","displayName":"Poland","isLoaded":false,"loadedDate":666804622.72068},{"isSelected":false,"id":"5F96C64B-E4FE-4F81-B066-255AF03ADFDC","fileName":"Portugal.json","displayName":"Portugal","isLoaded":false,"loadedDate":666804622.72934401},{"isSelected":false,"id":"3F2D14AC-FD9B-4407-868C-BFB21D6CA171","fileName":"Qatar.json","displayName":"Qatar","isLoaded":false,"loadedDate":666804622.73799098},{"isSelected":false,"id":"96E5FF57-EF45-433D-B6B4-B33D41389E5F","fileName":"Romania.json","displayName":"Romania","isLoaded":false,"loadedDate":666804622.74750304},{"isSelected":false,"id":"233555FA-6248-42C4-852F-87A15306D264","fileName":"Russia.json","displayName":"Russia","isLoaded":false,"loadedDate":666804622.75632799},{"isSelected":false,"id":"0553BA0E-9505-4793-99FF-6AFB008647BC","fileName":"Rwanda.json","displayName":"Rwanda","isLoaded":false,"loadedDate":666804622.764961},{"isSelected":false,"id":"A4B09E02-F497-4150-9E15-72585CF39E30","fileName":"Saint Kitts and Nevis.json","displayName":"Saint Kitts and Nevis","isLoaded":false,"loadedDate":666804622.77339995},{"isSelected":false,"id":"5DEFB7EB-DCFE-45A3-9C20-11D149459DAE","fileName":"Saint Lucia.json","displayName":"Saint Lucia","isLoaded":false,"loadedDate":666804622.785882},{"isSelected":false,"id":"F990B319-9B06-4FD0-A55F-34AED7EAD4F4","fileName":"Saint Vincent and the Grenadines.json","displayName":"Saint Vincent and the Grenadines","isLoaded":false,"loadedDate":666804622.79450798},{"isSelected":false,"id":"0AE6016B-EADC-4280-8D46-C5D5E579245A","fileName":"Samoa.json","displayName":"Samoa","isLoaded":false,"loadedDate":666804622.80316496},{"isSelected":false,"id":"3979DF48-9085-4747-B858-594F79EF0828","fileName":"San Marino.json","displayName":"San Marino","isLoaded":false,"loadedDate":666804622.81269205},{"isSelected":false,"id":"FF06D7A6-4706-4E28-B6C6-D341A7D7EF3F","fileName":"Sao Tome and Principe.json","displayName":"Sao Tome and Principe","isLoaded":false,"loadedDate":666804622.82154596},{"isSelected":false,"id":"AD70CDAD-DBDC-40FE-97D2-43D8CF2E1BF4","fileName":"Saudi Arabia.json","displayName":"Saudi Arabia","isLoaded":false,"loadedDate":666804622.83035398},{"isSelected":false,"id":"5221DCAB-461E-410B-87D8-4E0BEA17A329","fileName":"Senegal.json","displayName":"Senegal","isLoaded":false,"loadedDate":666804622.839185},{"isSelected":false,"id":"26263E2B-A71F-4F98-B68C-5F93FC0AE8F3","fileName":"Serbia.json","displayName":"Serbia","isLoaded":false,"loadedDate":666804622.84795296},{"isSelected":false,"id":"40A9282D-1235-4324-BE23-D7C40E876D0E","fileName":"Seychelles.json","displayName":"Seychelles","isLoaded":false,"loadedDate":666804622.85809898},{"isSelected":false,"id":"D838F27C-227D-463E-9A11-8AA0D0FA0C59","fileName":"Sierra Leone.json","displayName":"Sierra Leone","isLoaded":false,"loadedDate":666804622.86715698},{"isSelected":false,"id":"D6D8C2C5-AA6F-4F7B-AC21-4BB3D075C2DE","fileName":"Singapore.json","displayName":"Singapore","isLoaded":false,"loadedDate":666804622.87565696},{"isSelected":false,"id":"25DD6ED5-ACC7-4E27-8892-337BE684EC3E","fileName":"Slovakia.json","displayName":"Slovakia","isLoaded":false,"loadedDate":666804622.88486195},{"isSelected":false,"id":"8B175785-00A0-498A-9DD2-C03261CDA717","fileName":"Slovenia.json","displayName":"Slovenia","isLoaded":false,"loadedDate":666804622.89829695},{"isSelected":false,"id":"C49EEA40-6A29-4E5D-8444-DFA98F17365F","fileName":"Solomon Islands.json","displayName":"Solomon Islands","isLoaded":false,"loadedDate":666804622.90837097},{"isSelected":false,"id":"64142BEB-A686-4435-B2FE-B51589FD637F","fileName":"Somalia.json","displayName":"Somalia","isLoaded":false,"loadedDate":666804622.91887295},{"isSelected":false,"id":"03E9BEE4-27F3-4E01-8E3A-DB419BAB9E81","fileName":"South Africa.json","displayName":"South Africa","isLoaded":false,"loadedDate":666804622.92771399},{"isSelected":false,"id":"CA56A631-68D6-457C-958B-0E6737E35DA4","fileName":"South Sudan.json","displayName":"South Sudan","isLoaded":false,"loadedDate":666804622.93771505},{"isSelected":false,"id":"898EF266-35B1-4958-B26E-4A38B6A0EAB7","fileName":"Spain.json","displayName":"Spain","isLoaded":false,"loadedDate":666804622.95239997},{"isSelected":false,"id":"17CAEDDF-46E1-4AB9-AEBC-ADC92E13E8EE","fileName":"Sri Lanka.json","displayName":"Sri Lanka","isLoaded":false,"loadedDate":666804622.96139205},{"isSelected":false,"id":"B6ACD082-43AA-4A29-AAD9-8F101281EC12","fileName":"Sudan.json","displayName":"Sudan","isLoaded":false,"loadedDate":666804622.96993005},{"isSelected":false,"id":"0464874B-CDB1-4925-A457-4F3EB9FFC2B2","fileName":"Summer Olympics 2020.json","displayName":"Summer Olympics 2020","isLoaded":false,"loadedDate":666804622.97811306},{"isSelected":false,"id":"D6F53F12-4CD5-43B6-85C3-C4BC4E70350A","fileName":"Suriname.json","displayName":"Suriname","isLoaded":false,"loadedDate":666804622.98652697},{"isSelected":false,"id":"71A96FB2-66F4-4D5E-ABB6-A6D180734A97","fileName":"Sweden.json","displayName":"Sweden","isLoaded":false,"loadedDate":666804622.99521101},{"isSelected":false,"id":"A7EAE875-63D0-4B60-9FBB-A4695A54F439","fileName":"Switzerland.json","displayName":"Switzerland","isLoaded":false,"loadedDate":666804623.00359905},{"isSelected":false,"id":"804CC21F-97CE-44AB-BF41-8C784375B7FF","fileName":"Syria.json","displayName":"Syria","isLoaded":false,"loadedDate":666804623.01207602},{"isSelected":false,"id":"B83E8A93-13A1-4513-9048-1ED9D780C44A","fileName":"Taiwan*.json","displayName":"Taiwan*","isLoaded":false,"loadedDate":666804623.02057099},{"isSelected":false,"id":"7397CBD4-7016-406D-A2EF-FBF979FACA1A","fileName":"Tajikistan.json","displayName":"Tajikistan","isLoaded":false,"loadedDate":666804623.02881205},{"isSelected":false,"id":"DF184C9F-8FAD-4FE7-A112-57CF600CAB31","fileName":"Tanzania.json","displayName":"Tanzania","isLoaded":false,"loadedDate":666804623.03714001},{"isSelected":false,"id":"435FAEE2-9AA6-40B6-BB29-CE164BA8A743","fileName":"Thailand.json","displayName":"Thailand","isLoaded":false,"loadedDate":666804623.045681},{"isSelected":false,"id":"4BE60D5F-5EDE-422D-A65F-53216341EF5C","fileName":"Timor-Leste.json","displayName":"Timor-Leste","isLoaded":false,"loadedDate":666804623.05424798},{"isSelected":false,"id":"A2FD3814-F02C-4214-93E1-B27D6C446FF1","fileName":"Togo.json","displayName":"Togo","isLoaded":false,"loadedDate":666804623.06265295},{"isSelected":false,"id":"575238A7-E008-4EB1-9A7B-CB1A7A217F58","fileName":"Tonga.json","displayName":"Tonga","isLoaded":false,"loadedDate":666804623.07104397},{"isSelected":false,"id":"E50A8E2C-6016-43E1-AB14-66A7BE835BC8","fileName":"Trinidad and Tobago.json","displayName":"Trinidad and Tobago","isLoaded":false,"loadedDate":666804623.07884395},{"isSelected":false,"id":"FF34AD5E-6CE3-4AE0-87D3-A05B4683CF9D","fileName":"Tunisia.json","displayName":"Tunisia","isLoaded":false,"loadedDate":666804623.08740497},{"isSelected":false,"id":"A3F8F826-E26E-4436-AA53-FDD2AEA766E5","fileName":"Turkey.json","displayName":"Turkey","isLoaded":false,"loadedDate":666804623.09578598},{"isSelected":false,"id":"62A6F373-C631-45D6-97C3-83C128A8D484","fileName":"US.json","displayName":"US","isLoaded":false,"loadedDate":666804623.10451806},{"isSelected":false,"id":"715764E1-1EB3-415D-BE6E-329EA4ABE2E3","fileName":"Uganda.json","displayName":"Uganda","isLoaded":false,"loadedDate":666804623.11270905},{"isSelected":false,"id":"7390ABC1-3A26-43D4-8A53-E0B036C0D4C0","fileName":"Ukraine.json","displayName":"Ukraine","isLoaded":false,"loadedDate":666804623.12183106},{"isSelected":false,"id":"01CBCE7F-6F4D-48DF-BC94-44747C235251","fileName":"United Arab Emirates.json","displayName":"United Arab Emirates","isLoaded":false,"loadedDate":666804623.131024},{"isSelected":false,"id":"643F8B9E-27EE-43D7-A688-135C8C27CB10","fileName":"United Kingdom.json","displayName":"United Kingdom","isLoaded":false,"loadedDate":666804623.266819},{"isSelected":false,"id":"71EC435B-E000-4F7C-B309-FA208BEF481B","fileName":"United Kingdom - Anguilla.json","displayName":"United Kingdom - Anguilla","isLoaded":false,"loadedDate":666804623.13953102},{"isSelected":false,"id":"AC2BAB74-0C96-469F-BE67-5922A32D432A","fileName":"United Kingdom - Bermuda.json","displayName":"United Kingdom - Bermuda","isLoaded":false,"loadedDate":666804623.14771903},{"isSelected":false,"id":"2E628CFA-B5A1-4D38-AF04-AA54D9CD3DD2","fileName":"United Kingdom - British Virgin Islands.json","displayName":"United Kingdom - British Virgin Islands","isLoaded":false,"loadedDate":666804623.16357505},{"isSelected":false,"id":"DF1D8022-2BB1-4599-B80E-705A76BD85E4","fileName":"United Kingdom - Cayman Islands.json","displayName":"United Kingdom - Cayman Islands","isLoaded":false,"loadedDate":666804623.17495},{"isSelected":false,"id":"596032FD-A19B-4B5F-95F2-3FD4A0EDE839","fileName":"United Kingdom - Channel Islands.json","displayName":"United Kingdom - Channel Islands","isLoaded":false,"loadedDate":666804623.18065798},{"isSelected":false,"id":"1BBF9CF8-B589-434C-8977-32D4848F9747","fileName":"United Kingdom - Falkland Islands (Malvinas).json","displayName":"United Kingdom - Falkland Islands (Malvinas)","isLoaded":false,"loadedDate":666804623.18945706},{"isSelected":false,"id":"26CD7A0C-9283-435B-8F4A-E694FFFB639F","fileName":"United Kingdom - Gibraltar.json","displayName":"United Kingdom - Gibraltar","isLoaded":false,"loadedDate":666804623.19862998},{"isSelected":false,"id":"815F5A63-284B-4DD0-AEC3-536250478A37","fileName":"United Kingdom - Guernsey.json","displayName":"United Kingdom - Guernsey","isLoaded":false,"loadedDate":666804623.20743597},{"isSelected":false,"id":"234676F8-1AE8-4C51-B261-2329339CC26F","fileName":"United Kingdom - Isle of Man.json","displayName":"United Kingdom - Isle of Man","isLoaded":false,"loadedDate":666804623.21837199},{"isSelected":false,"id":"7162D07C-FBB4-49A0-A998-4B0B22DFD3AE","fileName":"United Kingdom - Jersey.json","displayName":"United Kingdom - Jersey","isLoaded":false,"loadedDate":666804623.23433995},{"isSelected":false,"id":"0F1DC3D7-CA2B-408F-8D44-163B40CBFD0B","fileName":"United Kingdom - Montserrat.json","displayName":"United Kingdom - Montserrat","isLoaded":false,"loadedDate":666804623.24213004},{"isSelected":false,"id":"43E919D3-6BF2-4F5C-81B8-D0F0C9927484","fileName":"United Kingdom - Saint Helena, Ascension and Tristan da Cunha.json","displayName":"United Kingdom - Saint Helena, Ascension and Tristan da Cunha","isLoaded":false,"loadedDate":666804623.25080097},{"isSelected":false,"id":"EB6E3BBC-4D90-4C71-8CB0-DAE97AE5DD02","fileName":"United Kingdom - Turks and Caicos Islands.json","displayName":"United Kingdom - Turks and Caicos Islands","isLoaded":false,"loadedDate":666804623.258564},{"isSelected":false,"id":"446E9BF5-CCA7-4372-A0F8-A40F9604E782","fileName":"Uruguay.json","displayName":"Uruguay","isLoaded":false,"loadedDate":666804623.27535605},{"isSelected":false,"id":"D3916A05-F76E-4946-A19E-80C61E54942D","fileName":"Uzbekistan.json","displayName":"Uzbekistan","isLoaded":false,"loadedDate":666804623.28399098},{"isSelected":false,"id":"C61A75D7-8D6D-4D85-AD10-924F63D73CE8","fileName":"Vanuatu.json","displayName":"Vanuatu","isLoaded":false,"loadedDate":666804623.29247701},{"isSelected":false,"id":"DFBDF8E7-E9B8-4F6D-8529-DE62B7C73E5D","fileName":"Venezuela.json","displayName":"Venezuela","isLoaded":false,"loadedDate":666804623.30096996},{"isSelected":false,"id":"0E2E7ECF-8BAF-4128-8481-5B7DC3A61BC4","fileName":"Vietnam.json","displayName":"Vietnam","isLoaded":false,"loadedDate":666804623.30954695},{"isSelected":false,"id":"D1E99837-E461-420F-9D12-371635873940","fileName":"West Bank and Gaza.json","displayName":"West Bank and Gaza","isLoaded":false,"loadedDate":666804623.31812},{"isSelected":false,"id":"64FC0D42-A73F-4977-938D-C2D1B177DF6B","fileName":"Winter Olympics 2022.json","displayName":"Winter Olympics 2022","isLoaded":false,"loadedDate":666804623.32655704},{"isSelected":false,"id":"A433F7CA-6CC3-4DE6-9AF5-916CE1B8BA39","fileName":"Yemen.json","displayName":"Yemen","isLoaded":false,"loadedDate":666804623.33522701},{"isSelected":false,"id":"447942B8-A794-4BD6-99FC-741C8FFEA5A0","fileName":"Zambia.json","displayName":"Zambia","isLoaded":false,"loadedDate":666804623.34385395},{"isSelected":false,"id":"BF8CA918-8210-47B2-8290-1BA9AFDDEF9E","fileName":"Zimbabwe.json","displayName":"Zimbabwe","isLoaded":false,"loadedDate":666804623.35279405}]}